[{"source": "AAEL027637", "target": "AAEL027637", "value": 2}, {"source": "AAEL027637", "target": "AAEL027637", "value": 2}, {"source": "AAEL027637", "target": "AAEL027637", "value": 4}, {"source": "AAEL027637", "target": "AAEL027637", "value": 4}, {"source": "AAEL027637", "target": "AAEL027637", "value": 4}, {"source": "AAEL027637", "target": "AAEL027637", "value": 4}, {"source": "AAEL027637", "target": "AAEL027637", "value": 6}, {"source": "AAEL027637", "target": "AAEL027637", "value": 8}, {"source": "AAEL027637", "target": "AAEL027637", "value": 10}, {"source": "AAEL027637", "target": "AAEL006381", "value": 9}, {"source": "AAEL027637", "target": "AAEL006381", "value": 11}, {"source": "AAEL027637", "target": "AAEL003318", "value": 6}, {"source": "AAEL027637", "target": "AAEL026602", "value": 11}, {"source": "AAEL027637", "target": "AAEL027637", "value": 13}, {"source": "AAEL027637", "target": "AAEL011756", "value": 5}, {"source": "AAEL027637", "target": "AAEL026602", "value": 5}, {"source": "AAEL027637", "target": "AAEL011756", "value": 7}, {"source": "AAEL027637", "target": "AAEL026602", "value": 7}, {"source": "AAEL027637", "target": "AAEL011756", "value": 7}, {"source": "AAEL027637", "target": "AAEL011756", "value": 9}, {"source": "AAEL027637", "target": "AAEL006381", "value": 5}, {"source": "AAEL027637", "target": "AAEL006381", "value": 7}, {"source": "AAEL027637", "target": "AAEL006381", "value": 6}, {"source": "AAEL027637", "target": "AAEL006381", "value": 8}, {"source": "AAEL027637", "target": "AAEL003318", "value": 7}, {"source": "AAEL027637", "target": "AAEL006381", "value": 9}, {"source": "AAEL006381", "target": "AAEL027637", "value": 9}, {"source": "AAEL006381", "target": "AAEL027637", "value": 11}, {"source": "AAEL006381", "target": "AAEL006381", "value": 2}, {"source": "AAEL006381", "target": "AAEL006381", "value": 2}, {"source": "AAEL006381", "target": "AAEL006381", "value": 4}, {"source": "AAEL006381", "target": "AAEL006381", "value": 4}, {"source": "AAEL006381", "target": "AAEL006381", "value": 6}, {"source": "AAEL006381", "target": "AAEL006381", "value": 6}, {"source": "AAEL006381", "target": "AAEL006381", "value": 6}, {"source": "AAEL006381", "target": "AAEL006381", "value": 6}, {"source": "AAEL006381", "target": "AAEL006381", "value": 8}, {"source": "AAEL006381", "target": "AAEL006381", "value": 10}, {"source": "AAEL006381", "target": "AAEL006381", "value": 12}, {"source": "AAEL006381", "target": "AAEL003318", "value": 7}, {"source": "AAEL006381", "target": "AAEL026602", "value": 12}, {"source": "AAEL006381", "target": "AAEL027637", "value": 14}, {"source": "AAEL006381", "target": "AAEL011756", "value": 6}, {"source": "AAEL006381", "target": "AAEL026602", "value": 6}, {"source": "AAEL006381", "target": "AAEL011756", "value": 8}, {"source": "AAEL006381", "target": "AAEL026602", "value": 8}, {"source": "AAEL006381", "target": "AAEL011756", "value": 8}, {"source": "AAEL006381", "target": "AAEL011756", "value": 10}, {"source": "AAEL006381", "target": "AAEL006381", "value": 6}, {"source": "AAEL006381", "target": "AAEL006381", "value": 8}, {"source": "AAEL006381", "target": "AAEL006381", "value": 5}, {"source": "AAEL006381", "target": "AAEL006381", "value": 7}, {"source": "AAEL006381", "target": "AAEL006381", "value": 9}, {"source": "AAEL006381", "target": "AAEL003318", "value": 8}, {"source": "AAEL006381", "target": "AAEL006381", "value": 10}, {"source": "AAEL003318", "target": "AAEL027637", "value": 6}, {"source": "AAEL003318", "target": "AAEL006381", "value": 7}, {"source": "AAEL003318", "target": "AAEL003318", "value": 2}, {"source": "AAEL003318", "target": "AAEL026602", "value": 7}, {"source": "AAEL003318", "target": "AAEL027637", "value": 9}, {"source": "AAEL003318", "target": "AAEL011756", "value": 3}, {"source": "AAEL003318", "target": "AAEL026602", "value": 3}, {"source": "AAEL003318", "target": "AAEL011756", "value": 5}, {"source": "AAEL003318", "target": "AAEL006381", "value": 3}, {"source": "AAEL003318", "target": "AAEL006381", "value": 4}, {"source": "AAEL003318", "target": "AAEL003318", "value": 3}, {"source": "AAEL003318", "target": "AAEL006381", "value": 5}, {"source": "AAEL026602", "target": "AAEL027637", "value": 11}, {"source": "AAEL026602", "target": "AAEL006381", "value": 12}, {"source": "AAEL026602", "target": "AAEL003318", "value": 7}, {"source": "AAEL026602", "target": "AAEL026602", "value": 2}, {"source": "AAEL026602", "target": "AAEL026602", "value": 4}, {"source": "AAEL026602", "target": "AAEL026602", "value": 6}, {"source": "AAEL026602", "target": "AAEL026602", "value": 8}, {"source": "AAEL026602", "target": "AAEL026602", "value": 10}, {"source": "AAEL026602", "target": "AAEL026602", "value": 12}, {"source": "AAEL026602", "target": "AAEL027637", "value": 7}, {"source": "AAEL026602", "target": "AAEL027637", "value": 7}, {"source": "AAEL026602", "target": "AAEL027637", "value": 9}, {"source": "AAEL026602", "target": "AAEL027637", "value": 10}, {"source": "AAEL026602", "target": "AAEL027637", "value": 11}, {"source": "AAEL026602", "target": "AAEL027637", "value": 12}, {"source": "AAEL026602", "target": "AAEL027637", "value": 12}, {"source": "AAEL026602", "target": "AAEL027637", "value": 14}, {"source": "AAEL026602", "target": "AAEL011756", "value": 8}, {"source": "AAEL026602", "target": "AAEL026602", "value": 8}, {"source": "AAEL026602", "target": "AAEL011756", "value": 10}, {"source": "AAEL026602", "target": "AAEL006381", "value": 8}, {"source": "AAEL026602", "target": "AAEL006381", "value": 9}, {"source": "AAEL026602", "target": "AAEL003318", "value": 8}, {"source": "AAEL026602", "target": "AAEL006381", "value": 4}, {"source": "AAEL026602", "target": "AAEL006381", "value": 6}, {"source": "AAEL026602", "target": "AAEL006381", "value": 8}, {"source": "AAEL026602", "target": "AAEL006381", "value": 10}, {"source": "AAEL027637", "target": "AAEL027637", "value": 13}, {"source": "AAEL027637", "target": "AAEL006381", "value": 14}, {"source": "AAEL027637", "target": "AAEL003318", "value": 9}, {"source": "AAEL027637", "target": "AAEL026602", "value": 7}, {"source": "AAEL027637", "target": "AAEL026602", "value": 7}, {"source": "AAEL027637", "target": "AAEL026602", "value": 9}, {"source": "AAEL027637", "target": "AAEL026602", "value": 10}, {"source": "AAEL027637", "target": "AAEL026602", "value": 11}, {"source": "AAEL027637", "target": "AAEL026602", "value": 12}, {"source": "AAEL027637", "target": "AAEL026602", "value": 12}, {"source": "AAEL027637", "target": "AAEL026602", "value": 14}, {"source": "AAEL027637", "target": "AAEL027637", "value": 2}, {"source": "AAEL027637", "target": "AAEL027637", "value": 2}, {"source": "AAEL027637", "target": "AAEL027637", "value": 2}, {"source": "AAEL027637", "target": "AAEL027637", "value": 2}, {"source": "AAEL027637", "target": "AAEL027637", "value": 4}, {"source": "AAEL027637", "target": "AAEL027637", "value": 4}, {"source": "AAEL027637", "target": "AAEL027637", "value": 6}, {"source": "AAEL027637", "target": "AAEL027637", "value": 7}, {"source": "AAEL027637", "target": "AAEL027637", "value": 8}, {"source": "AAEL027637", "target": "AAEL027637", "value": 9}, {"source": "AAEL027637", "target": "AAEL027637", "value": 9}, {"source": "AAEL027637", "target": "AAEL027637", "value": 4}, {"source": "AAEL027637", "target": "AAEL027637", "value": 4}, {"source": "AAEL027637", "target": "AAEL027637", "value": 4}, {"source": "AAEL027637", "target": "AAEL027637", "value": 4}, {"source": "AAEL027637", "target": "AAEL027637", "value": 4}, {"source": "AAEL027637", "target": "AAEL027637", "value": 7}, {"source": "AAEL027637", "target": "AAEL027637", "value": 6}, {"source": "AAEL027637", "target": "AAEL027637", "value": 6}, {"source": "AAEL027637", "target": "AAEL027637", "value": 6}, {"source": "AAEL027637", "target": "AAEL027637", "value": 6}, {"source": "AAEL027637", "target": "AAEL027637", "value": 6}, {"source": "AAEL027637", "target": "AAEL027637", "value": 6}, {"source": "AAEL027637", "target": "AAEL027637", "value": 6}, {"source": "AAEL027637", "target": "AAEL027637", "value": 6}, {"source": "AAEL027637", "target": "AAEL027637", "value": 6}, {"source": "AAEL027637", "target": "AAEL027637", "value": 6}, {"source": "AAEL027637", "target": "AAEL027637", "value": 8}, {"source": "AAEL027637", "target": "AAEL027637", "value": 8}, {"source": "AAEL027637", "target": "AAEL027637", "value": 8}, {"source": "AAEL027637", "target": "AAEL027637", "value": 8}, {"source": "AAEL027637", "target": "AAEL027637", "value": 6}, {"source": "AAEL027637", "target": "AAEL027637", "value": 8}, {"source": "AAEL027637", "target": "AAEL027637", "value": 9}, {"source": "AAEL027637", "target": "AAEL027637", "value": 10}, {"source": "AAEL027637", "target": "AAEL027637", "value": 11}, {"source": "AAEL027637", "target": "AAEL027637", "value": 11}, {"source": "AAEL027637", "target": "AAEL027637", "value": 8}, {"source": "AAEL027637", "target": "AAEL027637", "value": 9}, {"source": "AAEL027637", "target": "AAEL027637", "value": 8}, {"source": "AAEL027637", "target": "AAEL027637", "value": 10}, {"source": "AAEL027637", "target": "AAEL027637", "value": 8}, {"source": "AAEL027637", "target": "AAEL027637", "value": 8}, {"source": "AAEL027637", "target": "AAEL027637", "value": 8}, {"source": "AAEL027637", "target": "AAEL027637", "value": 8}, {"source": "AAEL027637", "target": "AAEL027637", "value": 8}, {"source": "AAEL027637", "target": "AAEL027637", "value": 10}, {"source": "AAEL027637", "target": "AAEL027637", "value": 7}, {"source": "AAEL027637", "target": "AAEL027637", "value": 9}, {"source": "AAEL027637", "target": "AAEL027637", "value": 10}, {"source": "AAEL027637", "target": "AAEL027637", "value": 11}, {"source": "AAEL027637", "target": "AAEL027637", "value": 12}, {"source": "AAEL027637", "target": "AAEL027637", "value": 12}, {"source": "AAEL027637", "target": "AAEL027637", "value": 9}, {"source": "AAEL027637", "target": "AAEL027637", "value": 10}, {"source": "AAEL027637", "target": "AAEL027637", "value": 7}, {"source": "AAEL027637", "target": "AAEL027637", "value": 10}, {"source": "AAEL027637", "target": "AAEL027637", "value": 8}, {"source": "AAEL027637", "target": "AAEL027637", "value": 10}, {"source": "AAEL027637", "target": "AAEL027637", "value": 11}, {"source": "AAEL027637", "target": "AAEL027637", "value": 12}, {"source": "AAEL027637", "target": "AAEL027637", "value": 13}, {"source": "AAEL027637", "target": "AAEL027637", "value": 13}, {"source": "AAEL027637", "target": "AAEL027637", "value": 10}, {"source": "AAEL027637", "target": "AAEL027637", "value": 12}, {"source": "AAEL027637", "target": "AAEL027637", "value": 10}, {"source": "AAEL027637", "target": "AAEL027637", "value": 12}, {"source": "AAEL027637", "target": "AAEL027637", "value": 9}, {"source": "AAEL027637", "target": "AAEL027637", "value": 11}, {"source": "AAEL027637", "target": "AAEL027637", "value": 12}, {"source": "AAEL027637", "target": "AAEL027637", "value": 13}, {"source": "AAEL027637", "target": "AAEL027637", "value": 14}, {"source": "AAEL027637", "target": "AAEL027637", "value": 14}, {"source": "AAEL027637", "target": "AAEL027637", "value": 9}, {"source": "AAEL027637", "target": "AAEL027637", "value": 11}, {"source": "AAEL027637", "target": "AAEL027637", "value": 12}, {"source": "AAEL027637", "target": "AAEL027637", "value": 13}, {"source": "AAEL027637", "target": "AAEL027637", "value": 14}, {"source": "AAEL027637", "target": "AAEL027637", "value": 14}, {"source": "AAEL027637", "target": "AAEL027637", "value": 16}, {"source": "AAEL027637", "target": "AAEL011756", "value": 10}, {"source": "AAEL027637", "target": "AAEL026602", "value": 10}, {"source": "AAEL027637", "target": "AAEL011756", "value": 12}, {"source": "AAEL027637", "target": "AAEL006381", "value": 10}, {"source": "AAEL027637", "target": "AAEL006381", "value": 11}, {"source": "AAEL027637", "target": "AAEL003318", "value": 10}, {"source": "AAEL027637", "target": "AAEL006381", "value": 5}, {"source": "AAEL027637", "target": "AAEL006381", "value": 5}, {"source": "AAEL027637", "target": "AAEL006381", "value": 7}, {"source": "AAEL027637", "target": "AAEL006381", "value": 8}, {"source": "AAEL027637", "target": "AAEL006381", "value": 9}, {"source": "AAEL027637", "target": "AAEL006381", "value": 10}, {"source": "AAEL027637", "target": "AAEL006381", "value": 10}, {"source": "AAEL027637", "target": "AAEL006381", "value": 12}, {"source": "AAEL027839", "target": "AAEL027839", "value": 2}, {"source": "AAEL027839", "target": "AAEL027839", "value": 3}, {"source": "AAEL027839", "target": "AAEL027839", "value": 3}, {"source": "AAEL027839", "target": "AAEL027839", "value": 2}, {"source": "AAEL027839", "target": "AAEL027839", "value": 2}, {"source": "AAEL027839", "target": "AAEL027839", "value": 2}, {"source": "AAEL027839", "target": "AAEL027839", "value": 3}, {"source": "AAEL027839", "target": "AAEL027839", "value": 2}, {"source": "AAEL027839", "target": "AAEL027839", "value": 4}, {"source": "AAEL027839", "target": "AAEL027839", "value": 4}, {"source": "AAEL027839", "target": "AAEL027839", "value": 5}, {"source": "AAEL027839", "target": "AAEL027839", "value": 6}, {"source": "AAEL027839", "target": "AAEL027839", "value": 6}, {"source": "AAEL027839", "target": "AAEL027839", "value": 7}, {"source": "AAEL027839", "target": "AAEL027839", "value": 8}, {"source": "AAEL027839", "target": "AAEL027839", "value": 8}, {"source": "AAEL027839", "target": "AAEL027839", "value": 9}, {"source": "AAEL027839", "target": "AAEL027839", "value": 10}, {"source": "AAEL027839", "target": "AAEL027839", "value": 11}, {"source": "AAEL027839", "target": "AAEL027839", "value": 11}, {"source": "AAEL027839", "target": "AAEL027839", "value": 12}, {"source": "AAEL027839", "target": "AAEL027839", "value": 4}, {"source": "AAEL027839", "target": "AAEL027839", "value": 4}, {"source": "AAEL027839", "target": "AAEL027839", "value": 5}, {"source": "AAEL027839", "target": "AAEL027839", "value": 6}, {"source": "AAEL027839", "target": "AAEL027839", "value": 6}, {"source": "AAEL027839", "target": "AAEL027839", "value": 7}, {"source": "AAEL027839", "target": "AAEL027839", "value": 8}, {"source": "AAEL027839", "target": "AAEL027839", "value": 8}, {"source": "AAEL027839", "target": "AAEL027839", "value": 9}, {"source": "AAEL027839", "target": "AAEL027839", "value": 10}, {"source": "AAEL027839", "target": "AAEL027839", "value": 11}, {"source": "AAEL027839", "target": "AAEL027839", "value": 11}, {"source": "AAEL027839", "target": "AAEL027839", "value": 12}, {"source": "AAEL027839", "target": "AAEL027839", "value": 4}, {"source": "AAEL027839", "target": "AAEL027839", "value": 5}, {"source": "AAEL027839", "target": "AAEL027839", "value": 4}, {"source": "AAEL027839", "target": "AAEL027839", "value": 5}, {"source": "AAEL027839", "target": "AAEL027839", "value": 6}, {"source": "AAEL027839", "target": "AAEL027839", "value": 3}, {"source": "AAEL027839", "target": "AAEL027839", "value": 4}, {"source": "AAEL027839", "target": "AAEL027839", "value": 4}, {"source": "AAEL027839", "target": "AAEL027839", "value": 3}, {"source": "AAEL027839", "target": "AAEL027839", "value": 4}, {"source": "AAEL027839", "target": "AAEL027839", "value": 4}, {"source": "AAEL027839", "target": "AAEL027839", "value": 4}, {"source": "AAEL027839", "target": "AAEL027839", "value": 3}, {"source": "AAEL027839", "target": "AAEL027839", "value": 4}, {"source": "AAEL027839", "target": "AAEL027839", "value": 4}, {"source": "AAEL027839", "target": "AAEL027839", "value": 5}, {"source": "AAEL027839", "target": "AAEL027839", "value": 5}, {"source": "AAEL027839", "target": "AAEL027839", "value": 6}, {"source": "AAEL027839", "target": "AAEL027839", "value": 4}, {"source": "AAEL027839", "target": "AAEL027839", "value": 5}, {"source": "AAEL027839", "target": "AAEL027839", "value": 5}, {"source": "AAEL027839", "target": "AAEL027839", "value": 4}, {"source": "AAEL027839", "target": "AAEL027839", "value": 6}, {"source": "AAEL027839", "target": "AAEL027839", "value": 7}, {"source": "AAEL027839", "target": "AAEL027839", "value": 8}, {"source": "AAEL027839", "target": "AAEL027839", "value": 9}, {"source": "AAEL027839", "target": "AAEL027839", "value": 9}, {"source": "AAEL027839", "target": "AAEL027839", "value": 10}, {"source": "AAEL027839", "target": "AAEL027839", "value": 5}, {"source": "AAEL027839", "target": "AAEL027839", "value": 5}, {"source": "AAEL027839", "target": "AAEL027839", "value": 6}, {"source": "AAEL027839", "target": "AAEL027839", "value": 7}, {"source": "AAEL027839", "target": "AAEL027839", "value": 7}, {"source": "AAEL027839", "target": "AAEL027839", "value": 8}, {"source": "AAEL027839", "target": "AAEL027839", "value": 9}, {"source": "AAEL027839", "target": "AAEL027839", "value": 9}, {"source": "AAEL027839", "target": "AAEL027839", "value": 10}, {"source": "AAEL027839", "target": "AAEL027839", "value": 11}, {"source": "AAEL027839", "target": "AAEL027839", "value": 12}, {"source": "AAEL027839", "target": "AAEL027839", "value": 12}, {"source": "AAEL027839", "target": "AAEL027839", "value": 13}, {"source": "AAEL027839", "target": "AAEL027839", "value": 5}, {"source": "AAEL027839", "target": "AAEL027839", "value": 6}, {"source": "AAEL027839", "target": "AAEL027839", "value": 5}, {"source": "AAEL027839", "target": "AAEL027839", "value": 6}, {"source": "AAEL027839", "target": "AAEL027839", "value": 7}, {"source": "AAEL027839", "target": "AAEL027839", "value": 6}, {"source": "AAEL027839", "target": "AAEL027839", "value": 7}, {"source": "AAEL027839", "target": "AAEL027839", "value": 8}, {"source": "AAEL027839", "target": "AAEL027839", "value": 6}, {"source": "AAEL027839", "target": "AAEL027839", "value": 7}, {"source": "AAEL027839", "target": "AAEL027839", "value": 7}, {"source": "AAEL027839", "target": "AAEL027839", "value": 8}, {"source": "AAEL027839", "target": "AAEL027839", "value": 6}, {"source": "AAEL027839", "target": "AAEL027839", "value": 7}, {"source": "AAEL027839", "target": "AAEL027839", "value": 6}, {"source": "AAEL027839", "target": "AAEL027839", "value": 7}, {"source": "AAEL027839", "target": "AAEL027839", "value": 6}, {"source": "AAEL027839", "target": "AAEL027839", "value": 7}, {"source": "AAEL027839", "target": "AAEL027839", "value": 7}, {"source": "AAEL027839", "target": "AAEL027839", "value": 8}, {"source": "AAEL027839", "target": "AAEL027839", "value": 8}, {"source": "AAEL027839", "target": "AAEL027839", "value": 8}, {"source": "AAEL027839", "target": "AAEL027839", "value": 9}, {"source": "AAEL027839", "target": "AAEL027839", "value": 9}, {"source": "AAEL027839", "target": "AAEL027839", "value": 5}, {"source": "AAEL027839", "target": "AAEL027839", "value": 6}, {"source": "AAEL027839", "target": "AAEL027839", "value": 6}, {"source": "AAEL027839", "target": "AAEL027839", "value": 7}, {"source": "AAEL027839", "target": "AAEL027839", "value": 5}, {"source": "AAEL027839", "target": "AAEL027839", "value": 6}, {"source": "AAEL027839", "target": "AAEL027839", "value": 6}, {"source": "AAEL027839", "target": "AAEL027839", "value": 7}, {"source": "AAEL027839", "target": "AAEL027839", "value": 5}, {"source": "AAEL027839", "target": "AAEL027839", "value": 6}, {"source": "AAEL027839", "target": "AAEL027839", "value": 6}, {"source": "AAEL027839", "target": "AAEL027839", "value": 5}, {"source": "AAEL027839", "target": "AAEL027839", "value": 6}, {"source": "AAEL027839", "target": "AAEL027839", "value": 6}, {"source": "AAEL027839", "target": "AAEL027839", "value": 6}, {"source": "AAEL027839", "target": "AAEL027839", "value": 6}, {"source": "AAEL027839", "target": "AAEL027839", "value": 7}, {"source": "AAEL027839", "target": "AAEL027839", "value": 8}, {"source": "AAEL027839", "target": "AAEL027839", "value": 8}, {"source": "AAEL027839", "target": "AAEL027839", "value": 9}, {"source": "AAEL027839", "target": "AAEL027839", "value": 10}, {"source": "AAEL027839", "target": "AAEL027839", "value": 10}, {"source": "AAEL027839", "target": "AAEL027839", "value": 11}, {"source": "AAEL027839", "target": "AAEL027839", "value": 12}, {"source": "AAEL027839", "target": "AAEL027839", "value": 13}, {"source": "AAEL027839", "target": "AAEL027839", "value": 13}, {"source": "AAEL027839", "target": "AAEL027839", "value": 14}, {"source": "AAEL027839", "target": "AAEL027839", "value": 6}, {"source": "AAEL027839", "target": "AAEL027839", "value": 6}, {"source": "AAEL027839", "target": "AAEL027839", "value": 7}, {"source": "AAEL027839", "target": "AAEL027839", "value": 8}, {"source": "AAEL027839", "target": "AAEL027839", "value": 8}, {"source": "AAEL027839", "target": "AAEL027839", "value": 9}, {"source": "AAEL027839", "target": "AAEL027839", "value": 10}, {"source": "AAEL027839", "target": "AAEL027839", "value": 10}, {"source": "AAEL027839", "target": "AAEL027839", "value": 11}, {"source": "AAEL027839", "target": "AAEL027839", "value": 12}, {"source": "AAEL027839", "target": "AAEL027839", "value": 13}, {"source": "AAEL027839", "target": "AAEL027839", "value": 13}, {"source": "AAEL027839", "target": "AAEL027839", "value": 14}, {"source": "AAEL027839", "target": "AAEL027839", "value": 8}, {"source": "AAEL027839", "target": "AAEL027839", "value": 9}, {"source": "AAEL027839", "target": "AAEL027839", "value": 6}, {"source": "AAEL027839", "target": "AAEL027839", "value": 7}, {"source": "AAEL027839", "target": "AAEL027839", "value": 8}, {"source": "AAEL027839", "target": "AAEL027839", "value": 8}, {"source": "AAEL027839", "target": "AAEL027839", "value": 9}, {"source": "AAEL027839", "target": "AAEL027839", "value": 9}, {"source": "AAEL027839", "target": "AAEL027839", "value": 9}, {"source": "AAEL027839", "target": "AAEL027839", "value": 10}, {"source": "AAEL027839", "target": "AAEL027839", "value": 10}, {"source": "AAEL027839", "target": "AAEL027839", "value": 7}, {"source": "AAEL027839", "target": "AAEL027839", "value": 8}, {"source": "AAEL027839", "target": "AAEL027839", "value": 9}, {"source": "AAEL027839", "target": "AAEL027839", "value": 7}, {"source": "AAEL027839", "target": "AAEL027839", "value": 8}, {"source": "AAEL027839", "target": "AAEL027839", "value": 8}, {"source": "AAEL027839", "target": "AAEL027839", "value": 9}, {"source": "AAEL027839", "target": "AAEL027839", "value": 7}, {"source": "AAEL027839", "target": "AAEL027839", "value": 8}, {"source": "AAEL027839", "target": "AAEL027839", "value": 8}, {"source": "AAEL027839", "target": "AAEL027839", "value": 9}, {"source": "AAEL027839", "target": "AAEL027839", "value": 7}, {"source": "AAEL027839", "target": "AAEL027839", "value": 8}, {"source": "AAEL027839", "target": "AAEL027839", "value": 7}, {"source": "AAEL027839", "target": "AAEL027839", "value": 8}, {"source": "AAEL027839", "target": "AAEL027839", "value": 7}, {"source": "AAEL027839", "target": "AAEL027839", "value": 8}, {"source": "AAEL027839", "target": "AAEL027839", "value": 8}, {"source": "AAEL027839", "target": "AAEL027839", "value": 9}, {"source": "AAEL027839", "target": "AAEL027839", "value": 9}, {"source": "AAEL027839", "target": "AAEL027839", "value": 9}, {"source": "AAEL027839", "target": "AAEL027839", "value": 10}, {"source": "AAEL027839", "target": "AAEL027839", "value": 10}, {"source": "AAEL027839", "target": "AAEL027839", "value": 7}, {"source": "AAEL027839", "target": "AAEL027839", "value": 8}, {"source": "AAEL027839", "target": "AAEL027839", "value": 8}, {"source": "AAEL027839", "target": "AAEL027839", "value": 9}, {"source": "AAEL027839", "target": "AAEL027839", "value": 9}, {"source": "AAEL027839", "target": "AAEL027839", "value": 9}, {"source": "AAEL027839", "target": "AAEL027839", "value": 10}, {"source": "AAEL027839", "target": "AAEL027839", "value": 10}, {"source": "AAEL027839", "target": "AAEL027839", "value": 6}, {"source": "AAEL027839", "target": "AAEL027839", "value": 7}, {"source": "AAEL027839", "target": "AAEL027839", "value": 7}, {"source": "AAEL027839", "target": "AAEL027839", "value": 8}, {"source": "AAEL027839", "target": "AAEL027839", "value": 6}, {"source": "AAEL027839", "target": "AAEL027839", "value": 8}, {"source": "AAEL027839", "target": "AAEL027839", "value": 9}, {"source": "AAEL027839", "target": "AAEL027839", "value": 10}, {"source": "AAEL027839", "target": "AAEL027839", "value": 11}, {"source": "AAEL027839", "target": "AAEL027839", "value": 11}, {"source": "AAEL027839", "target": "AAEL027839", "value": 12}, {"source": "AAEL027839", "target": "AAEL027839", "value": 7}, {"source": "AAEL027839", "target": "AAEL027839", "value": 7}, {"source": "AAEL027839", "target": "AAEL027839", "value": 8}, {"source": "AAEL027839", "target": "AAEL027839", "value": 9}, {"source": "AAEL027839", "target": "AAEL027839", "value": 9}, {"source": "AAEL027839", "target": "AAEL027839", "value": 10}, {"source": "AAEL027839", "target": "AAEL027839", "value": 11}, {"source": "AAEL027839", "target": "AAEL027839", "value": 11}, {"source": "AAEL027839", "target": "AAEL027839", "value": 12}, {"source": "AAEL027839", "target": "AAEL027839", "value": 13}, {"source": "AAEL027839", "target": "AAEL027839", "value": 14}, {"source": "AAEL027839", "target": "AAEL027839", "value": 14}, {"source": "AAEL027839", "target": "AAEL027839", "value": 15}, {"source": "AAEL027839", "target": "AAEL027839", "value": 10}, {"source": "AAEL027839", "target": "AAEL027839", "value": 11}, {"source": "AAEL027839", "target": "AAEL027839", "value": 12}, {"source": "AAEL027839", "target": "AAEL027839", "value": 9}, {"source": "AAEL027839", "target": "AAEL027839", "value": 10}, {"source": "AAEL027839", "target": "AAEL027839", "value": 9}, {"source": "AAEL027839", "target": "AAEL027839", "value": 10}, {"source": "AAEL027839", "target": "AAEL027839", "value": 10}, {"source": "AAEL027839", "target": "AAEL027839", "value": 10}, {"source": "AAEL027839", "target": "AAEL027839", "value": 11}, {"source": "AAEL027839", "target": "AAEL027839", "value": 11}, {"source": "AAEL027839", "target": "AAEL027839", "value": 9}, {"source": "AAEL027839", "target": "AAEL027839", "value": 10}, {"source": "AAEL027839", "target": "AAEL027839", "value": 10}, {"source": "AAEL027839", "target": "AAEL027839", "value": 10}, {"source": "AAEL027839", "target": "AAEL027839", "value": 11}, {"source": "AAEL027839", "target": "AAEL027839", "value": 11}, {"source": "AAEL027839", "target": "AAEL027839", "value": 9}, {"source": "AAEL027839", "target": "AAEL027839", "value": 10}, {"source": "AAEL027839", "target": "AAEL027839", "value": 10}, {"source": "AAEL027839", "target": "AAEL027839", "value": 10}, {"source": "AAEL027839", "target": "AAEL027839", "value": 11}, {"source": "AAEL027839", "target": "AAEL027839", "value": 11}, {"source": "AAEL027839", "target": "AAEL027839", "value": 8}, {"source": "AAEL027839", "target": "AAEL027839", "value": 9}, {"source": "AAEL027839", "target": "AAEL027839", "value": 10}, {"source": "AAEL027839", "target": "AAEL027839", "value": 8}, {"source": "AAEL027839", "target": "AAEL027839", "value": 9}, {"source": "AAEL027839", "target": "AAEL027839", "value": 9}, {"source": "AAEL027839", "target": "AAEL027839", "value": 10}, {"source": "AAEL027839", "target": "AAEL027839", "value": 8}, {"source": "AAEL027839", "target": "AAEL027839", "value": 9}, {"source": "AAEL027839", "target": "AAEL027839", "value": 9}, {"source": "AAEL027839", "target": "AAEL027839", "value": 10}, {"source": "AAEL027839", "target": "AAEL027839", "value": 10}, {"source": "AAEL027839", "target": "AAEL027839", "value": 10}, {"source": "AAEL027839", "target": "AAEL027839", "value": 11}, {"source": "AAEL027839", "target": "AAEL027839", "value": 11}, {"source": "AAEL027839", "target": "AAEL027839", "value": 8}, {"source": "AAEL027839", "target": "AAEL027839", "value": 9}, {"source": "AAEL027839", "target": "AAEL027839", "value": 9}, {"source": "AAEL027839", "target": "AAEL027839", "value": 10}, {"source": "AAEL027839", "target": "AAEL027839", "value": 10}, {"source": "AAEL027839", "target": "AAEL027839", "value": 10}, {"source": "AAEL027839", "target": "AAEL027839", "value": 11}, {"source": "AAEL027839", "target": "AAEL027839", "value": 11}, {"source": "AAEL027839", "target": "AAEL027839", "value": 8}, {"source": "AAEL027839", "target": "AAEL027839", "value": 9}, {"source": "AAEL027839", "target": "AAEL027839", "value": 9}, {"source": "AAEL027839", "target": "AAEL027839", "value": 10}, {"source": "AAEL027839", "target": "AAEL027839", "value": 10}, {"source": "AAEL027839", "target": "AAEL027839", "value": 10}, {"source": "AAEL027839", "target": "AAEL027839", "value": 11}, {"source": "AAEL027839", "target": "AAEL027839", "value": 11}, {"source": "AAEL027839", "target": "AAEL027839", "value": 7}, {"source": "AAEL027839", "target": "AAEL027839", "value": 9}, {"source": "AAEL027839", "target": "AAEL027839", "value": 10}, {"source": "AAEL027839", "target": "AAEL027839", "value": 11}, {"source": "AAEL027839", "target": "AAEL027839", "value": 12}, {"source": "AAEL027839", "target": "AAEL027839", "value": 12}, {"source": "AAEL027839", "target": "AAEL027839", "value": 13}, {"source": "AAEL027839", "target": "AAEL027839", "value": 8}, {"source": "AAEL027839", "target": "AAEL027839", "value": 8}, {"source": "AAEL027839", "target": "AAEL027839", "value": 9}, {"source": "AAEL027839", "target": "AAEL027839", "value": 10}, {"source": "AAEL027839", "target": "AAEL027839", "value": 10}, {"source": "AAEL027839", "target": "AAEL027839", "value": 11}, {"source": "AAEL027839", "target": "AAEL027839", "value": 12}, {"source": "AAEL027839", "target": "AAEL027839", "value": 12}, {"source": "AAEL027839", "target": "AAEL027839", "value": 13}, {"source": "AAEL027839", "target": "AAEL027839", "value": 14}, {"source": "AAEL027839", "target": "AAEL027839", "value": 15}, {"source": "AAEL027839", "target": "AAEL027839", "value": 15}, {"source": "AAEL027839", "target": "AAEL027839", "value": 16}, {"source": "AAEL027839", "target": "AAEL027839", "value": 8}, {"source": "AAEL027839", "target": "AAEL027839", "value": 8}, {"source": "AAEL027839", "target": "AAEL027839", "value": 9}, {"source": "AAEL027839", "target": "AAEL027839", "value": 10}, {"source": "AAEL027839", "target": "AAEL027839", "value": 10}, {"source": "AAEL027839", "target": "AAEL027839", "value": 11}, {"source": "AAEL027839", "target": "AAEL027839", "value": 12}, {"source": "AAEL027839", "target": "AAEL027839", "value": 12}, {"source": "AAEL027839", "target": "AAEL027839", "value": 13}, {"source": "AAEL027839", "target": "AAEL027839", "value": 14}, {"source": "AAEL027839", "target": "AAEL027839", "value": 15}, {"source": "AAEL027839", "target": "AAEL027839", "value": 15}, {"source": "AAEL027839", "target": "AAEL027839", "value": 16}, {"source": "AAEL027839", "target": "AAEL027839", "value": 11}, {"source": "AAEL027839", "target": "AAEL027839", "value": 12}, {"source": "AAEL027839", "target": "AAEL027839", "value": 13}, {"source": "AAEL027839", "target": "AAEL027839", "value": 10}, {"source": "AAEL027839", "target": "AAEL027839", "value": 11}, {"source": "AAEL027839", "target": "AAEL027839", "value": 11}, {"source": "AAEL027839", "target": "AAEL027839", "value": 11}, {"source": "AAEL027839", "target": "AAEL027839", "value": 12}, {"source": "AAEL027839", "target": "AAEL027839", "value": 12}, {"source": "AAEL027839", "target": "AAEL027839", "value": 10}, {"source": "AAEL027839", "target": "AAEL027839", "value": 11}, {"source": "AAEL027839", "target": "AAEL027839", "value": 11}, {"source": "AAEL027839", "target": "AAEL027839", "value": 11}, {"source": "AAEL027839", "target": "AAEL027839", "value": 12}, {"source": "AAEL027839", "target": "AAEL027839", "value": 12}, {"source": "AAEL027839", "target": "AAEL027839", "value": 9}, {"source": "AAEL027839", "target": "AAEL027839", "value": 10}, {"source": "AAEL027839", "target": "AAEL027839", "value": 10}, {"source": "AAEL027839", "target": "AAEL027839", "value": 11}, {"source": "AAEL027839", "target": "AAEL027839", "value": 11}, {"source": "AAEL027839", "target": "AAEL027839", "value": 11}, {"source": "AAEL027839", "target": "AAEL027839", "value": 12}, {"source": "AAEL027839", "target": "AAEL027839", "value": 12}, {"source": "AAEL027839", "target": "AAEL027839", "value": 9}, {"source": "AAEL027839", "target": "AAEL027839", "value": 10}, {"source": "AAEL027839", "target": "AAEL027839", "value": 10}, {"source": "AAEL027839", "target": "AAEL027839", "value": 11}, {"source": "AAEL027839", "target": "AAEL027839", "value": 11}, {"source": "AAEL027839", "target": "AAEL027839", "value": 11}, {"source": "AAEL027839", "target": "AAEL027839", "value": 12}, {"source": "AAEL027839", "target": "AAEL027839", "value": 12}, {"source": "AAEL027839", "target": "AAEL027839", "value": 8}, {"source": "AAEL027839", "target": "AAEL027839", "value": 10}, {"source": "AAEL027839", "target": "AAEL027839", "value": 11}, {"source": "AAEL027839", "target": "AAEL027839", "value": 12}, {"source": "AAEL027839", "target": "AAEL027839", "value": 13}, {"source": "AAEL027839", "target": "AAEL027839", "value": 13}, {"source": "AAEL027839", "target": "AAEL027839", "value": 14}, {"source": "AAEL027839", "target": "AAEL027839", "value": 9}, {"source": "AAEL027839", "target": "AAEL027839", "value": 9}, {"source": "AAEL027839", "target": "AAEL027839", "value": 10}, {"source": "AAEL027839", "target": "AAEL027839", "value": 11}, {"source": "AAEL027839", "target": "AAEL027839", "value": 11}, {"source": "AAEL027839", "target": "AAEL027839", "value": 12}, {"source": "AAEL027839", "target": "AAEL027839", "value": 13}, {"source": "AAEL027839", "target": "AAEL027839", "value": 13}, {"source": "AAEL027839", "target": "AAEL027839", "value": 14}, {"source": "AAEL027839", "target": "AAEL027839", "value": 15}, {"source": "AAEL027839", "target": "AAEL027839", "value": 16}, {"source": "AAEL027839", "target": "AAEL027839", "value": 16}, {"source": "AAEL027839", "target": "AAEL027839", "value": 17}, {"source": "AAEL027839", "target": "AAEL027839", "value": 12}, {"source": "AAEL027839", "target": "AAEL027839", "value": 13}, {"source": "AAEL027839", "target": "AAEL027839", "value": 14}, {"source": "AAEL027839", "target": "AAEL027839", "value": 9}, {"source": "AAEL027839", "target": "AAEL027839", "value": 11}, {"source": "AAEL027839", "target": "AAEL027839", "value": 12}, {"source": "AAEL027839", "target": "AAEL027839", "value": 13}, {"source": "AAEL027839", "target": "AAEL027839", "value": 14}, {"source": "AAEL027839", "target": "AAEL027839", "value": 14}, {"source": "AAEL027839", "target": "AAEL027839", "value": 15}, {"source": "AAEL027839", "target": "AAEL027839", "value": 9}, {"source": "AAEL027839", "target": "AAEL027839", "value": 11}, {"source": "AAEL027839", "target": "AAEL027839", "value": 12}, {"source": "AAEL027839", "target": "AAEL027839", "value": 13}, {"source": "AAEL027839", "target": "AAEL027839", "value": 14}, {"source": "AAEL027839", "target": "AAEL027839", "value": 14}, {"source": "AAEL027839", "target": "AAEL027839", "value": 15}, {"source": "AAEL027839", "target": "AAEL027839", "value": 10}, {"source": "AAEL027839", "target": "AAEL027839", "value": 10}, {"source": "AAEL027839", "target": "AAEL027839", "value": 11}, {"source": "AAEL027839", "target": "AAEL027839", "value": 12}, {"source": "AAEL027839", "target": "AAEL027839", "value": 12}, {"source": "AAEL027839", "target": "AAEL027839", "value": 13}, {"source": "AAEL027839", "target": "AAEL027839", "value": 14}, {"source": "AAEL027839", "target": "AAEL027839", "value": 14}, {"source": "AAEL027839", "target": "AAEL027839", "value": 15}, {"source": "AAEL027839", "target": "AAEL027839", "value": 16}, {"source": "AAEL027839", "target": "AAEL027839", "value": 17}, {"source": "AAEL027839", "target": "AAEL027839", "value": 17}, {"source": "AAEL027839", "target": "AAEL027839", "value": 18}, {"source": "AAEL027839", "target": "AAEL027839", "value": 16}, {"source": "AAEL027839", "target": "AAEL027839", "value": 17}, {"source": "AAEL027839", "target": "AAEL027839", "value": 10}, {"source": "AAEL027839", "target": "AAEL027839", "value": 12}, {"source": "AAEL027839", "target": "AAEL027839", "value": 13}, {"source": "AAEL027839", "target": "AAEL027839", "value": 14}, {"source": "AAEL027839", "target": "AAEL027839", "value": 15}, {"source": "AAEL027839", "target": "AAEL027839", "value": 15}, {"source": "AAEL027839", "target": "AAEL027839", "value": 16}, {"source": "AAEL027839", "target": "AAEL027839", "value": 11}, {"source": "AAEL027839", "target": "AAEL027839", "value": 11}, {"source": "AAEL027839", "target": "AAEL027839", "value": 12}, {"source": "AAEL027839", "target": "AAEL027839", "value": 13}, {"source": "AAEL027839", "target": "AAEL027839", "value": 13}, {"source": "AAEL027839", "target": "AAEL027839", "value": 14}, {"source": "AAEL027839", "target": "AAEL027839", "value": 15}, {"source": "AAEL027839", "target": "AAEL027839", "value": 15}, {"source": "AAEL027839", "target": "AAEL027839", "value": 16}, {"source": "AAEL027839", "target": "AAEL027839", "value": 17}, {"source": "AAEL027839", "target": "AAEL027839", "value": 18}, {"source": "AAEL027839", "target": "AAEL027839", "value": 18}, {"source": "AAEL027839", "target": "AAEL027839", "value": 19}, {"source": "AAEL027839", "target": "AAEL027839", "value": 11}, {"source": "AAEL027839", "target": "AAEL027839", "value": 11}, {"source": "AAEL027839", "target": "AAEL027839", "value": 12}, {"source": "AAEL027839", "target": "AAEL027839", "value": 13}, {"source": "AAEL027839", "target": "AAEL027839", "value": 13}, {"source": "AAEL027839", "target": "AAEL027839", "value": 14}, {"source": "AAEL027839", "target": "AAEL027839", "value": 15}, {"source": "AAEL027839", "target": "AAEL027839", "value": 15}, {"source": "AAEL027839", "target": "AAEL027839", "value": 16}, {"source": "AAEL027839", "target": "AAEL027839", "value": 17}, {"source": "AAEL027839", "target": "AAEL027839", "value": 18}, {"source": "AAEL027839", "target": "AAEL027839", "value": 18}, {"source": "AAEL027839", "target": "AAEL027839", "value": 19}, {"source": "AAEL027839", "target": "AAEL027839", "value": 17}, {"source": "AAEL027839", "target": "AAEL027839", "value": 18}, {"source": "AAEL027839", "target": "AAEL027839", "value": 12}, {"source": "AAEL027839", "target": "AAEL027839", "value": 12}, {"source": "AAEL027839", "target": "AAEL027839", "value": 13}, {"source": "AAEL027839", "target": "AAEL027839", "value": 14}, {"source": "AAEL027839", "target": "AAEL027839", "value": 14}, {"source": "AAEL027839", "target": "AAEL027839", "value": 15}, {"source": "AAEL027839", "target": "AAEL027839", "value": 16}, {"source": "AAEL027839", "target": "AAEL027839", "value": 16}, {"source": "AAEL027839", "target": "AAEL027839", "value": 17}, {"source": "AAEL027839", "target": "AAEL027839", "value": 18}, {"source": "AAEL027839", "target": "AAEL027839", "value": 19}, {"source": "AAEL027839", "target": "AAEL027839", "value": 19}, {"source": "AAEL027839", "target": "AAEL027839", "value": 20}, {"source": "AAEL027839", "target": "AAEL003318", "value": 3}, {"source": "AAEL027839", "target": "AAEL003318", "value": 3}, {"source": "AAEL027839", "target": "AAEL003318", "value": 4}, {"source": "AAEL027839", "target": "AAEL003318", "value": 5}, {"source": "AAEL027839", "target": "AAEL003318", "value": 5}, {"source": "AAEL027839", "target": "AAEL003318", "value": 6}, {"source": "AAEL027839", "target": "AAEL003318", "value": 7}, {"source": "AAEL027839", "target": "AAEL003318", "value": 7}, {"source": "AAEL027839", "target": "AAEL003318", "value": 8}, {"source": "AAEL027839", "target": "AAEL003318", "value": 9}, {"source": "AAEL027839", "target": "AAEL003318", "value": 10}, {"source": "AAEL027839", "target": "AAEL003318", "value": 10}, {"source": "AAEL027839", "target": "AAEL003318", "value": 11}, {"source": "AAEL027839", "target": "AAEL003318", "value": 4}, {"source": "AAEL027839", "target": "AAEL027839", "value": 4}, {"source": "AAEL027839", "target": "AAEL003318", "value": 3}, {"source": "AAEL027839", "target": "AAEL027839", "value": 3}, {"source": "AAEL027839", "target": "AAEL003318", "value": 5}, {"source": "AAEL027839", "target": "AAEL027839", "value": 5}, {"source": "AAEL027839", "target": "AAEL003318", "value": 6}, {"source": "AAEL027839", "target": "AAEL027839", "value": 6}, {"source": "AAEL027839", "target": "AAEL003318", "value": 5}, {"source": "AAEL027839", "target": "AAEL027839", "value": 5}, {"source": "AAEL027839", "target": "AAEL003318", "value": 6}, {"source": "AAEL027839", "target": "AAEL027839", "value": 6}, {"source": "AAEL027839", "target": "AAEL003318", "value": 5}, {"source": "AAEL027839", "target": "AAEL027839", "value": 5}, {"source": "AAEL027839", "target": "AAEL003318", "value": 5}, {"source": "AAEL027839", "target": "AAEL027839", "value": 5}, {"source": "AAEL027839", "target": "AAEL003318", "value": 6}, {"source": "AAEL027839", "target": "AAEL027839", "value": 6}, {"source": "AAEL027839", "target": "AAEL003318", "value": 7}, {"source": "AAEL027839", "target": "AAEL027839", "value": 7}, {"source": "AAEL027839", "target": "AAEL003318", "value": 7}, {"source": "AAEL027839", "target": "AAEL027839", "value": 7}, {"source": "AAEL027839", "target": "AAEL003318", "value": 8}, {"source": "AAEL027839", "target": "AAEL027839", "value": 8}, {"source": "AAEL027839", "target": "AAEL003318", "value": 7}, {"source": "AAEL027839", "target": "AAEL027839", "value": 7}, {"source": "AAEL027839", "target": "AAEL003318", "value": 8}, {"source": "AAEL027839", "target": "AAEL027839", "value": 8}, {"source": "AAEL027839", "target": "AAEL003318", "value": 8}, {"source": "AAEL027839", "target": "AAEL027839", "value": 8}, {"source": "AAEL027839", "target": "AAEL003318", "value": 9}, {"source": "AAEL027839", "target": "AAEL027839", "value": 9}, {"source": "AAEL027839", "target": "AAEL003318", "value": 9}, {"source": "AAEL027839", "target": "AAEL027839", "value": 9}, {"source": "AAEL027839", "target": "AAEL003318", "value": 10}, {"source": "AAEL027839", "target": "AAEL027839", "value": 10}, {"source": "AAEL027839", "target": "AAEL003318", "value": 9}, {"source": "AAEL027839", "target": "AAEL027839", "value": 9}, {"source": "AAEL027839", "target": "AAEL003318", "value": 10}, {"source": "AAEL027839", "target": "AAEL027839", "value": 10}, {"source": "AAEL027839", "target": "AAEL003318", "value": 10}, {"source": "AAEL027839", "target": "AAEL027839", "value": 10}, {"source": "AAEL027839", "target": "AAEL003318", "value": 11}, {"source": "AAEL027839", "target": "AAEL027839", "value": 11}, {"source": "AAEL027839", "target": "AAEL003318", "value": 11}, {"source": "AAEL027839", "target": "AAEL027839", "value": 11}, {"source": "AAEL027839", "target": "AAEL003318", "value": 12}, {"source": "AAEL027839", "target": "AAEL027839", "value": 12}, {"source": "AAEL027839", "target": "AAEL003318", "value": 12}, {"source": "AAEL027839", "target": "AAEL027839", "value": 12}, {"source": "AAEL027839", "target": "AAEL003318", "value": 13}, {"source": "AAEL027839", "target": "AAEL027839", "value": 13}, {"source": "AAEL027839", "target": "AAEL003318", "value": 12}, {"source": "AAEL027839", "target": "AAEL027839", "value": 12}, {"source": "AAEL027839", "target": "AAEL003318", "value": 13}, {"source": "AAEL027839", "target": "AAEL027839", "value": 13}, {"source": "AAEL027839", "target": "AAEL003318", "value": 13}, {"source": "AAEL027839", "target": "AAEL027839", "value": 13}, {"source": "AAEL027839", "target": "AAEL003318", "value": 14}, {"source": "AAEL027839", "target": "AAEL027839", "value": 14}, {"source": "AAEL006381", "target": "AAEL006381", "value": 2}, {"source": "AAEL006381", "target": "AAEL006381", "value": 2}, {"source": "AAEL006381", "target": "AAEL006381", "value": 2}, {"source": "AAEL006381", "target": "AAEL006381", "value": 4}, {"source": "AAEL006381", "target": "AAEL006381", "value": 4}, {"source": "AAEL006381", "target": "AAEL006381", "value": 4}, {"source": "AAEL006381", "target": "AAEL006381", "value": 4}, {"source": "AAEL006381", "target": "AAEL006381", "value": 4}, {"source": "AAEL006381", "target": "AAEL006381", "value": 4}, {"source": "AAEL006381", "target": "AAEL006381", "value": 4}, {"source": "AAEL006381", "target": "AAEL006381", "value": 4}, {"source": "AAEL006381", "target": "AAEL006381", "value": 4}, {"source": "AAEL006381", "target": "AAEL006381", "value": 4}, {"source": "AAEL006381", "target": "AAEL006381", "value": 5}, {"source": "AAEL006381", "target": "AAEL006381", "value": 4}, {"source": "AAEL006381", "target": "AAEL006381", "value": 4}, {"source": "AAEL006381", "target": "AAEL006381", "value": 4}, {"source": "AAEL006381", "target": "AAEL006381", "value": 4}, {"source": "AAEL006381", "target": "AAEL006381", "value": 6}, {"source": "AAEL006381", "target": "AAEL006381", "value": 6}, {"source": "AAEL006381", "target": "AAEL006381", "value": 6}, {"source": "AAEL006381", "target": "AAEL006381", "value": 6}, {"source": "AAEL006381", "target": "AAEL006381", "value": 6}, {"source": "AAEL006381", "target": "AAEL006381", "value": 6}, {"source": "AAEL006381", "target": "AAEL006381", "value": 7}, {"source": "AAEL006381", "target": "AAEL006381", "value": 7}, {"source": "AAEL006381", "target": "AAEL006381", "value": 6}, {"source": "AAEL006381", "target": "AAEL006381", "value": 6}, {"source": "AAEL006381", "target": "AAEL006381", "value": 6}, {"source": "AAEL006381", "target": "AAEL006381", "value": 6}, {"source": "AAEL006381", "target": "AAEL006381", "value": 6}, {"source": "AAEL006381", "target": "AAEL006381", "value": 5}, {"source": "AAEL006381", "target": "AAEL006381", "value": 6}, {"source": "AAEL006381", "target": "AAEL006381", "value": 6}, {"source": "AAEL006381", "target": "AAEL006381", "value": 7}, {"source": "AAEL006381", "target": "AAEL006381", "value": 7}, {"source": "AAEL006381", "target": "AAEL006381", "value": 6}, {"source": "AAEL006381", "target": "AAEL006381", "value": 6}, {"source": "AAEL006381", "target": "AAEL006381", "value": 6}, {"source": "AAEL006381", "target": "AAEL006381", "value": 6}, {"source": "AAEL006381", "target": "AAEL006381", "value": 6}, {"source": "AAEL006381", "target": "AAEL006381", "value": 6}, {"source": "AAEL006381", "target": "AAEL006381", "value": 8}, {"source": "AAEL006381", "target": "AAEL006381", "value": 6}, {"source": "AAEL006381", "target": "AAEL006381", "value": 6}, {"source": "AAEL006381", "target": "AAEL006381", "value": 8}, {"source": "AAEL006381", "target": "AAEL006381", "value": 8}, {"source": "AAEL006381", "target": "AAEL006381", "value": 8}, {"source": "AAEL006381", "target": "AAEL006381", "value": 8}, {"source": "AAEL006381", "target": "AAEL006381", "value": 8}, {"source": "AAEL006381", "target": "AAEL006381", "value": 7}, {"source": "AAEL006381", "target": "AAEL006381", "value": 8}, {"source": "AAEL006381", "target": "AAEL006381", "value": 8}, {"source": "AAEL006381", "target": "AAEL006381", "value": 7}, {"source": "AAEL006381", "target": "AAEL006381", "value": 8}, {"source": "AAEL006381", "target": "AAEL006381", "value": 8}, {"source": "AAEL006381", "target": "AAEL006381", "value": 8}, {"source": "AAEL006381", "target": "AAEL006381", "value": 8}, {"source": "AAEL006381", "target": "AAEL006381", "value": 9}, {"source": "AAEL006381", "target": "AAEL006381", "value": 9}, {"source": "AAEL006381", "target": "AAEL006381", "value": 9}, {"source": "AAEL006381", "target": "AAEL006381", "value": 8}, {"source": "AAEL006381", "target": "AAEL006381", "value": 7}, {"source": "AAEL006381", "target": "AAEL006381", "value": 8}, {"source": "AAEL006381", "target": "AAEL006381", "value": 8}, {"source": "AAEL006381", "target": "AAEL006381", "value": 7}, {"source": "AAEL006381", "target": "AAEL006381", "value": 8}, {"source": "AAEL006381", "target": "AAEL006381", "value": 8}, {"source": "AAEL006381", "target": "AAEL006381", "value": 8}, {"source": "AAEL006381", "target": "AAEL006381", "value": 8}, {"source": "AAEL006381", "target": "AAEL006381", "value": 10}, {"source": "AAEL006381", "target": "AAEL006381", "value": 10}, {"source": "AAEL006381", "target": "AAEL006381", "value": 8}, {"source": "AAEL006381", "target": "AAEL006381", "value": 8}, {"source": "AAEL006381", "target": "AAEL006381", "value": 10}, {"source": "AAEL006381", "target": "AAEL006381", "value": 10}, {"source": "AAEL006381", "target": "AAEL006381", "value": 10}, {"source": "AAEL006381", "target": "AAEL006381", "value": 10}, {"source": "AAEL006381", "target": "AAEL006381", "value": 10}, {"source": "AAEL006381", "target": "AAEL006381", "value": 10}, {"source": "AAEL006381", "target": "AAEL006381", "value": 10}, {"source": "AAEL006381", "target": "AAEL006381", "value": 11}, {"source": "AAEL006381", "target": "AAEL006381", "value": 12}, {"source": "AAEL006381", "target": "AAEL006381", "value": 12}, {"source": "AAEL006381", "target": "AAEL006381", "value": 12}, {"source": "AAEL006381", "target": "AAEL006381", "value": 10}, {"source": "AAEL006381", "target": "AAEL006381", "value": 11}, {"source": "AAEL006381", "target": "AAEL006381", "value": 9}, {"source": "AAEL006381", "target": "AAEL006381", "value": 10}, {"source": "AAEL006381", "target": "AAEL006381", "value": 10}, {"source": "AAEL006381", "target": "AAEL006381", "value": 10}, {"source": "AAEL006381", "target": "AAEL006381", "value": 9}, {"source": "AAEL006381", "target": "AAEL006381", "value": 10}, {"source": "AAEL006381", "target": "AAEL006381", "value": 10}, {"source": "AAEL006381", "target": "AAEL006381", "value": 10}, {"source": "AAEL006381", "target": "AAEL006381", "value": 9}, {"source": "AAEL006381", "target": "AAEL006381", "value": 10}, {"source": "AAEL006381", "target": "AAEL006381", "value": 10}, {"source": "AAEL006381", "target": "AAEL006381", "value": 10}, {"source": "AAEL006381", "target": "AAEL006381", "value": 8}, {"source": "AAEL006381", "target": "AAEL006381", "value": 8}, {"source": "AAEL006381", "target": "AAEL006381", "value": 10}, {"source": "AAEL006381", "target": "AAEL006381", "value": 11}, {"source": "AAEL006381", "target": "AAEL006381", "value": 12}, {"source": "AAEL006381", "target": "AAEL006381", "value": 13}, {"source": "AAEL006381", "target": "AAEL006381", "value": 13}, {"source": "AAEL006381", "target": "AAEL006381", "value": 13}, {"source": "AAEL006381", "target": "AAEL006381", "value": 11}, {"source": "AAEL006381", "target": "AAEL006381", "value": 12}, {"source": "AAEL006381", "target": "AAEL006381", "value": 12}, {"source": "AAEL006381", "target": "AAEL006381", "value": 12}, {"source": "AAEL006381", "target": "AAEL006381", "value": 10}, {"source": "AAEL006381", "target": "AAEL006381", "value": 10}, {"source": "AAEL006381", "target": "AAEL006381", "value": 12}, {"source": "AAEL006381", "target": "AAEL006381", "value": 12}, {"source": "AAEL006381", "target": "AAEL006381", "value": 10}, {"source": "AAEL006381", "target": "AAEL006381", "value": 10}, {"source": "AAEL006381", "target": "AAEL006381", "value": 12}, {"source": "AAEL006381", "target": "AAEL006381", "value": 12}, {"source": "AAEL006381", "target": "AAEL006381", "value": 14}, {"source": "AAEL006381", "target": "AAEL006381", "value": 15}, {"source": "AAEL006381", "target": "AAEL006381", "value": 12}, {"source": "AAEL006381", "target": "AAEL006381", "value": 13}, {"source": "AAEL006381", "target": "AAEL006381", "value": 14}, {"source": "AAEL006381", "target": "AAEL006381", "value": 14}, {"source": "AAEL006381", "target": "AAEL006381", "value": 14}, {"source": "AAEL006381", "target": "AAEL006381", "value": 12}, {"source": "AAEL006381", "target": "AAEL006381", "value": 13}, {"source": "AAEL006381", "target": "AAEL006381", "value": 14}, {"source": "AAEL006381", "target": "AAEL006381", "value": 14}, {"source": "AAEL006381", "target": "AAEL006381", "value": 14}, {"source": "AAEL006381", "target": "AAEL006381", "value": 12}, {"source": "AAEL006381", "target": "AAEL006381", "value": 13}, {"source": "AAEL006381", "target": "AAEL006381", "value": 14}, {"source": "AAEL006381", "target": "AAEL006381", "value": 14}, {"source": "AAEL006381", "target": "AAEL006381", "value": 14}, {"source": "AAEL006381", "target": "AAEL006381", "value": 15}, {"source": "AAEL006381", "target": "AAEL006381", "value": 16}, {"source": "AAEL006381", "target": "AAEL003318", "value": 14}, {"source": "AAEL006381", "target": "AAEL003318", "value": 15}, {"source": "AAEL006381", "target": "AAEL027637", "value": 9}, {"source": "AAEL006381", "target": "AAEL027637", "value": 8}, {"source": "AAEL006381", "target": "AAEL027637", "value": 8}, {"source": "AAEL006381", "target": "AAEL027637", "value": 8}, {"source": "AAEL006381", "target": "AAEL027637", "value": 8}, {"source": "AAEL006381", "target": "AAEL027637", "value": 10}, {"source": "AAEL006381", "target": "AAEL027637", "value": 10}, {"source": "AAEL006381", "target": "AAEL027637", "value": 11}, {"source": "AAEL006381", "target": "AAEL027637", "value": 12}, {"source": "AAEL006381", "target": "AAEL027637", "value": 10}, {"source": "AAEL006381", "target": "AAEL027637", "value": 11}, {"source": "AAEL006381", "target": "AAEL027637", "value": 12}, {"source": "AAEL006381", "target": "AAEL027637", "value": 10}, {"source": "AAEL006381", "target": "AAEL027637", "value": 11}, {"source": "AAEL006381", "target": "AAEL027637", "value": 12}, {"source": "AAEL006381", "target": "AAEL027637", "value": 11}, {"source": "AAEL006381", "target": "AAEL027637", "value": 12}, {"source": "AAEL006381", "target": "AAEL027637", "value": 13}, {"source": "AAEL006381", "target": "AAEL027637", "value": 14}, {"source": "AAEL006381", "target": "AAEL027637", "value": 14}, {"source": "AAEL006381", "target": "AAEL027637", "value": 14}, {"source": "AAEL006381", "target": "AAEL027637", "value": 12}, {"source": "AAEL006381", "target": "AAEL027637", "value": 13}, {"source": "AAEL006381", "target": "AAEL027637", "value": 12}, {"source": "AAEL006381", "target": "AAEL027637", "value": 13}, {"source": "AAEL006381", "target": "AAEL027637", "value": 12}, {"source": "AAEL006381", "target": "AAEL027637", "value": 13}, {"source": "AAEL006381", "target": "AAEL027637", "value": 12}, {"source": "AAEL006381", "target": "AAEL027637", "value": 13}, {"source": "AAEL006381", "target": "AAEL027637", "value": 14}, {"source": "AAEL006381", "target": "AAEL027637", "value": 15}, {"source": "AAEL006381", "target": "AAEL027637", "value": 15}, {"source": "AAEL006381", "target": "AAEL027637", "value": 15}, {"source": "AAEL006381", "target": "AAEL027637", "value": 15}, {"source": "AAEL006381", "target": "AAEL027637", "value": 11}, {"source": "AAEL006381", "target": "AAEL027637", "value": 12}, {"source": "AAEL006381", "target": "AAEL027637", "value": 13}, {"source": "AAEL006381", "target": "AAEL027637", "value": 14}, {"source": "AAEL006381", "target": "AAEL027637", "value": 12}, {"source": "AAEL006381", "target": "AAEL027637", "value": 13}, {"source": "AAEL006381", "target": "AAEL027637", "value": 14}, {"source": "AAEL006381", "target": "AAEL027637", "value": 17}, {"source": "AAEL006381", "target": "AAEL027637", "value": 17}, {"source": "AAEL006381", "target": "AAEL027637", "value": 13}, {"source": "AAEL006381", "target": "AAEL027637", "value": 14}, {"source": "AAEL006381", "target": "AAEL027637", "value": 15}, {"source": "AAEL006381", "target": "AAEL027637", "value": 16}, {"source": "AAEL006381", "target": "AAEL027637", "value": 16}, {"source": "AAEL006381", "target": "AAEL027637", "value": 16}, {"source": "AAEL006381", "target": "AAEL027637", "value": 13}, {"source": "AAEL006381", "target": "AAEL027637", "value": 14}, {"source": "AAEL006381", "target": "AAEL027637", "value": 15}, {"source": "AAEL006381", "target": "AAEL027637", "value": 16}, {"source": "AAEL006381", "target": "AAEL027637", "value": 16}, {"source": "AAEL006381", "target": "AAEL027637", "value": 16}, {"source": "AAEL006381", "target": "AAEL027637", "value": 13}, {"source": "AAEL006381", "target": "AAEL027637", "value": 14}, {"source": "AAEL006381", "target": "AAEL027637", "value": 15}, {"source": "AAEL006381", "target": "AAEL027637", "value": 16}, {"source": "AAEL006381", "target": "AAEL027637", "value": 16}, {"source": "AAEL006381", "target": "AAEL027637", "value": 16}, {"source": "AAEL006381", "target": "AAEL027637", "value": 18}, {"source": "AAEL006381", "target": "AAEL027637", "value": 18}, {"source": "AAEL006381", "target": "AAEL003318", "value": 11}, {"source": "AAEL006381", "target": "AAEL003318", "value": 12}, {"source": "AAEL006381", "target": "AAEL011756", "value": 6}, {"source": "AAEL006381", "target": "AAEL026602", "value": 6}, {"source": "AAEL006381", "target": "AAEL011756", "value": 7}, {"source": "AAEL006381", "target": "AAEL026602", "value": 7}, {"source": "AAEL006381", "target": "AAEL011756", "value": 9}, {"source": "AAEL006381", "target": "AAEL026602", "value": 9}, {"source": "AAEL006381", "target": "AAEL011756", "value": 8}, {"source": "AAEL006381", "target": "AAEL026602", "value": 8}, {"source": "AAEL006381", "target": "AAEL011756", "value": 8}, {"source": "AAEL006381", "target": "AAEL026602", "value": 8}, {"source": "AAEL006381", "target": "AAEL011756", "value": 8}, {"source": "AAEL006381", "target": "AAEL026602", "value": 8}, {"source": "AAEL006381", "target": "AAEL011756", "value": 10}, {"source": "AAEL006381", "target": "AAEL026602", "value": 10}, {"source": "AAEL003318", "target": "AAEL006381", "value": 14}, {"source": "AAEL003318", "target": "AAEL006381", "value": 15}, {"source": "AAEL003318", "target": "AAEL003318", "value": 2}, {"source": "AAEL003318", "target": "AAEL003318", "value": 4}, {"source": "AAEL003318", "target": "AAEL003318", "value": 4}, {"source": "AAEL003318", "target": "AAEL003318", "value": 6}, {"source": "AAEL003318", "target": "AAEL003318", "value": 7}, {"source": "AAEL003318", "target": "AAEL003318", "value": 6}, {"source": "AAEL003318", "target": "AAEL003318", "value": 7}, {"source": "AAEL003318", "target": "AAEL003318", "value": 8}, {"source": "AAEL003318", "target": "AAEL003318", "value": 10}, {"source": "AAEL003318", "target": "AAEL003318", "value": 12}, {"source": "AAEL003318", "target": "AAEL003318", "value": 14}, {"source": "AAEL003318", "target": "AAEL027637", "value": 17}, {"source": "AAEL003318", "target": "AAEL027637", "value": 17}, {"source": "AAEL003318", "target": "AAEL003318", "value": 4}, {"source": "AAEL003318", "target": "AAEL003318", "value": 5}, {"source": "AAEL003318", "target": "AAEL003318", "value": 7}, {"source": "AAEL003318", "target": "AAEL003318", "value": 9}, {"source": "AAEL003318", "target": "AAEL003318", "value": 11}, {"source": "AAEL003318", "target": "AAEL011756", "value": 9}, {"source": "AAEL003318", "target": "AAEL026602", "value": 9}, {"source": "AAEL003318", "target": "AAEL027839", "value": 3}, {"source": "AAEL003318", "target": "AAEL027839", "value": 3}, {"source": "AAEL003318", "target": "AAEL027839", "value": 4}, {"source": "AAEL003318", "target": "AAEL027839", "value": 5}, {"source": "AAEL003318", "target": "AAEL027839", "value": 5}, {"source": "AAEL003318", "target": "AAEL027839", "value": 6}, {"source": "AAEL003318", "target": "AAEL027839", "value": 7}, {"source": "AAEL003318", "target": "AAEL027839", "value": 7}, {"source": "AAEL003318", "target": "AAEL027839", "value": 8}, {"source": "AAEL003318", "target": "AAEL027839", "value": 9}, {"source": "AAEL003318", "target": "AAEL027839", "value": 10}, {"source": "AAEL003318", "target": "AAEL027839", "value": 10}, {"source": "AAEL003318", "target": "AAEL027839", "value": 11}, {"source": "AAEL003318", "target": "AAEL003318", "value": 2}, {"source": "AAEL003318", "target": "AAEL003318", "value": 4}, {"source": "AAEL003318", "target": "AAEL027839", "value": 4}, {"source": "AAEL003318", "target": "AAEL003318", "value": 5}, {"source": "AAEL003318", "target": "AAEL027839", "value": 5}, {"source": "AAEL003318", "target": "AAEL027839", "value": 3}, {"source": "AAEL027839", "target": "AAEL027839", "value": 3}, {"source": "AAEL003318", "target": "AAEL027839", "value": 5}, {"source": "AAEL027839", "target": "AAEL027839", "value": 5}, {"source": "AAEL003318", "target": "AAEL027839", "value": 5}, {"source": "AAEL027839", "target": "AAEL027839", "value": 5}, {"source": "AAEL003318", "target": "AAEL027839", "value": 6}, {"source": "AAEL027839", "target": "AAEL027839", "value": 6}, {"source": "AAEL003318", "target": "AAEL027839", "value": 7}, {"source": "AAEL027839", "target": "AAEL027839", "value": 7}, {"source": "AAEL003318", "target": "AAEL027839", "value": 7}, {"source": "AAEL027839", "target": "AAEL027839", "value": 7}, {"source": "AAEL003318", "target": "AAEL027839", "value": 8}, {"source": "AAEL027839", "target": "AAEL027839", "value": 8}, {"source": "AAEL003318", "target": "AAEL027839", "value": 9}, {"source": "AAEL027839", "target": "AAEL027839", "value": 9}, {"source": "AAEL003318", "target": "AAEL027839", "value": 9}, {"source": "AAEL027839", "target": "AAEL027839", "value": 9}, {"source": "AAEL003318", "target": "AAEL027839", "value": 10}, {"source": "AAEL027839", "target": "AAEL027839", "value": 10}, {"source": "AAEL003318", "target": "AAEL027839", "value": 11}, {"source": "AAEL027839", "target": "AAEL027839", "value": 11}, {"source": "AAEL003318", "target": "AAEL027839", "value": 12}, {"source": "AAEL027839", "target": "AAEL027839", "value": 12}, {"source": "AAEL003318", "target": "AAEL027839", "value": 12}, {"source": "AAEL027839", "target": "AAEL027839", "value": 12}, {"source": "AAEL003318", "target": "AAEL027839", "value": 13}, {"source": "AAEL027839", "target": "AAEL027839", "value": 13}, {"source": "AAEL003318", "target": "AAEL027839", "value": 4}, {"source": "AAEL027839", "target": "AAEL027839", "value": 4}, {"source": "AAEL003318", "target": "AAEL027839", "value": 5}, {"source": "AAEL027839", "target": "AAEL027839", "value": 5}, {"source": "AAEL003318", "target": "AAEL027839", "value": 5}, {"source": "AAEL027839", "target": "AAEL027839", "value": 5}, {"source": "AAEL003318", "target": "AAEL027839", "value": 6}, {"source": "AAEL027839", "target": "AAEL027839", "value": 6}, {"source": "AAEL003318", "target": "AAEL027839", "value": 6}, {"source": "AAEL027839", "target": "AAEL027839", "value": 6}, {"source": "AAEL003318", "target": "AAEL027839", "value": 7}, {"source": "AAEL027839", "target": "AAEL027839", "value": 7}, {"source": "AAEL003318", "target": "AAEL027839", "value": 8}, {"source": "AAEL027839", "target": "AAEL027839", "value": 8}, {"source": "AAEL003318", "target": "AAEL027839", "value": 8}, {"source": "AAEL027839", "target": "AAEL027839", "value": 8}, {"source": "AAEL003318", "target": "AAEL027839", "value": 9}, {"source": "AAEL027839", "target": "AAEL027839", "value": 9}, {"source": "AAEL003318", "target": "AAEL027839", "value": 10}, {"source": "AAEL027839", "target": "AAEL027839", "value": 10}, {"source": "AAEL003318", "target": "AAEL027839", "value": 10}, {"source": "AAEL027839", "target": "AAEL027839", "value": 10}, {"source": "AAEL003318", "target": "AAEL027839", "value": 11}, {"source": "AAEL027839", "target": "AAEL027839", "value": 11}, {"source": "AAEL003318", "target": "AAEL027839", "value": 12}, {"source": "AAEL027839", "target": "AAEL027839", "value": 12}, {"source": "AAEL003318", "target": "AAEL027839", "value": 13}, {"source": "AAEL027839", "target": "AAEL027839", "value": 13}, {"source": "AAEL003318", "target": "AAEL027839", "value": 13}, {"source": "AAEL027839", "target": "AAEL027839", "value": 13}, {"source": "AAEL003318", "target": "AAEL027839", "value": 14}, {"source": "AAEL027839", "target": "AAEL027839", "value": 14}, {"source": "AAEL003318", "target": "AAEL003318", "value": 4}, {"source": "AAEL027839", "target": "AAEL003318", "value": 4}, {"source": "AAEL003318", "target": "AAEL003318", "value": 5}, {"source": "AAEL027839", "target": "AAEL003318", "value": 5}, {"source": "AAEL003318", "target": "AAEL003318", "value": 2}, {"source": "AAEL003318", "target": "AAEL027839", "value": 2}, {"source": "AAEL027839", "target": "AAEL003318", "value": 2}, {"source": "AAEL027839", "target": "AAEL027839", "value": 2}, {"source": "AAEL003318", "target": "AAEL003318", "value": 4}, {"source": "AAEL003318", "target": "AAEL027839", "value": 4}, {"source": "AAEL027839", "target": "AAEL003318", "value": 4}, {"source": "AAEL027839", "target": "AAEL027839", "value": 4}, {"source": "AAEL003318", "target": "AAEL003318", "value": 6}, {"source": "AAEL003318", "target": "AAEL027839", "value": 6}, {"source": "AAEL027839", "target": "AAEL003318", "value": 6}, {"source": "AAEL027839", "target": "AAEL027839", "value": 6}, {"source": "AAEL003318", "target": "AAEL003318", "value": 7}, {"source": "AAEL003318", "target": "AAEL027839", "value": 7}, {"source": "AAEL027839", "target": "AAEL003318", "value": 7}, {"source": "AAEL027839", "target": "AAEL027839", "value": 7}, {"source": "AAEL003318", "target": "AAEL003318", "value": 6}, {"source": "AAEL003318", "target": "AAEL027839", "value": 6}, {"source": "AAEL027839", "target": "AAEL003318", "value": 6}, {"source": "AAEL027839", "target": "AAEL027839", "value": 6}, {"source": "AAEL003318", "target": "AAEL003318", "value": 7}, {"source": "AAEL003318", "target": "AAEL027839", "value": 7}, {"source": "AAEL027839", "target": "AAEL003318", "value": 7}, {"source": "AAEL027839", "target": "AAEL027839", "value": 7}, {"source": "AAEL003318", "target": "AAEL003318", "value": 8}, {"source": "AAEL003318", "target": "AAEL027839", "value": 8}, {"source": "AAEL027839", "target": "AAEL003318", "value": 8}, {"source": "AAEL027839", "target": "AAEL027839", "value": 8}, {"source": "AAEL027637", "target": "AAEL006381", "value": 11}, {"source": "AAEL027637", "target": "AAEL006381", "value": 8}, {"source": "AAEL027637", "target": "AAEL006381", "value": 8}, {"source": "AAEL027637", "target": "AAEL006381", "value": 8}, {"source": "AAEL027637", "target": "AAEL006381", "value": 8}, {"source": "AAEL027637", "target": "AAEL006381", "value": 9}, {"source": "AAEL027637", "target": "AAEL006381", "value": 10}, {"source": "AAEL027637", "target": "AAEL006381", "value": 10}, {"source": "AAEL027637", "target": "AAEL006381", "value": 11}, {"source": "AAEL027637", "target": "AAEL006381", "value": 12}, {"source": "AAEL027637", "target": "AAEL006381", "value": 13}, {"source": "AAEL027637", "target": "AAEL006381", "value": 13}, {"source": "AAEL027637", "target": "AAEL006381", "value": 13}, {"source": "AAEL027637", "target": "AAEL006381", "value": 10}, {"source": "AAEL027637", "target": "AAEL006381", "value": 10}, {"source": "AAEL027637", "target": "AAEL006381", "value": 12}, {"source": "AAEL027637", "target": "AAEL006381", "value": 12}, {"source": "AAEL027637", "target": "AAEL006381", "value": 12}, {"source": "AAEL027637", "target": "AAEL006381", "value": 13}, {"source": "AAEL027637", "target": "AAEL006381", "value": 14}, {"source": "AAEL027637", "target": "AAEL006381", "value": 14}, {"source": "AAEL027637", "target": "AAEL006381", "value": 14}, {"source": "AAEL027637", "target": "AAEL006381", "value": 11}, {"source": "AAEL027637", "target": "AAEL006381", "value": 12}, {"source": "AAEL027637", "target": "AAEL006381", "value": 12}, {"source": "AAEL027637", "target": "AAEL006381", "value": 12}, {"source": "AAEL027637", "target": "AAEL006381", "value": 11}, {"source": "AAEL027637", "target": "AAEL006381", "value": 11}, {"source": "AAEL027637", "target": "AAEL006381", "value": 13}, {"source": "AAEL027637", "target": "AAEL006381", "value": 13}, {"source": "AAEL027637", "target": "AAEL006381", "value": 13}, {"source": "AAEL027637", "target": "AAEL006381", "value": 14}, {"source": "AAEL027637", "target": "AAEL006381", "value": 15}, {"source": "AAEL027637", "target": "AAEL006381", "value": 15}, {"source": "AAEL027637", "target": "AAEL006381", "value": 15}, {"source": "AAEL027637", "target": "AAEL006381", "value": 12}, {"source": "AAEL027637", "target": "AAEL006381", "value": 13}, {"source": "AAEL027637", "target": "AAEL006381", "value": 13}, {"source": "AAEL027637", "target": "AAEL006381", "value": 13}, {"source": "AAEL027637", "target": "AAEL006381", "value": 12}, {"source": "AAEL027637", "target": "AAEL006381", "value": 12}, {"source": "AAEL027637", "target": "AAEL006381", "value": 14}, {"source": "AAEL027637", "target": "AAEL006381", "value": 14}, {"source": "AAEL027637", "target": "AAEL006381", "value": 14}, {"source": "AAEL027637", "target": "AAEL006381", "value": 15}, {"source": "AAEL027637", "target": "AAEL006381", "value": 16}, {"source": "AAEL027637", "target": "AAEL006381", "value": 16}, {"source": "AAEL027637", "target": "AAEL006381", "value": 16}, {"source": "AAEL027637", "target": "AAEL006381", "value": 14}, {"source": "AAEL027637", "target": "AAEL006381", "value": 15}, {"source": "AAEL027637", "target": "AAEL006381", "value": 16}, {"source": "AAEL027637", "target": "AAEL006381", "value": 16}, {"source": "AAEL027637", "target": "AAEL006381", "value": 16}, {"source": "AAEL027637", "target": "AAEL006381", "value": 14}, {"source": "AAEL027637", "target": "AAEL006381", "value": 15}, {"source": "AAEL027637", "target": "AAEL006381", "value": 16}, {"source": "AAEL027637", "target": "AAEL006381", "value": 16}, {"source": "AAEL027637", "target": "AAEL006381", "value": 16}, {"source": "AAEL027637", "target": "AAEL006381", "value": 15}, {"source": "AAEL027637", "target": "AAEL006381", "value": 17}, {"source": "AAEL027637", "target": "AAEL006381", "value": 18}, {"source": "AAEL027637", "target": "AAEL006381", "value": 17}, {"source": "AAEL027637", "target": "AAEL006381", "value": 18}, {"source": "AAEL027637", "target": "AAEL003318", "value": 17}, {"source": "AAEL027637", "target": "AAEL003318", "value": 17}, {"source": "AAEL027637", "target": "AAEL027637", "value": 2}, {"source": "AAEL027637", "target": "AAEL027637", "value": 2}, {"source": "AAEL027637", "target": "AAEL027637", "value": 4}, {"source": "AAEL027637", "target": "AAEL027637", "value": 4}, {"source": "AAEL027637", "target": "AAEL027637", "value": 4}, {"source": "AAEL027637", "target": "AAEL027637", "value": 4}, {"source": "AAEL027637", "target": "AAEL027637", "value": 4}, {"source": "AAEL027637", "target": "AAEL027637", "value": 6}, {"source": "AAEL027637", "target": "AAEL027637", "value": 6}, {"source": "AAEL027637", "target": "AAEL027637", "value": 6}, {"source": "AAEL027637", "target": "AAEL027637", "value": 6}, {"source": "AAEL027637", "target": "AAEL027637", "value": 6}, {"source": "AAEL027637", "target": "AAEL027637", "value": 8}, {"source": "AAEL027637", "target": "AAEL027637", "value": 8}, {"source": "AAEL027637", "target": "AAEL027637", "value": 8}, {"source": "AAEL027637", "target": "AAEL027637", "value": 8}, {"source": "AAEL027637", "target": "AAEL027637", "value": 8}, {"source": "AAEL027637", "target": "AAEL027637", "value": 8}, {"source": "AAEL027637", "target": "AAEL027637", "value": 10}, {"source": "AAEL027637", "target": "AAEL027637", "value": 10}, {"source": "AAEL027637", "target": "AAEL027637", "value": 10}, {"source": "AAEL027637", "target": "AAEL027637", "value": 10}, {"source": "AAEL027637", "target": "AAEL027637", "value": 10}, {"source": "AAEL027637", "target": "AAEL027637", "value": 10}, {"source": "AAEL027637", "target": "AAEL027637", "value": 10}, {"source": "AAEL027637", "target": "AAEL027637", "value": 10}, {"source": "AAEL027637", "target": "AAEL027637", "value": 10}, {"source": "AAEL027637", "target": "AAEL027637", "value": 10}, {"source": "AAEL027637", "target": "AAEL027637", "value": 10}, {"source": "AAEL027637", "target": "AAEL027637", "value": 11}, {"source": "AAEL027637", "target": "AAEL027637", "value": 12}, {"source": "AAEL027637", "target": "AAEL027637", "value": 13}, {"source": "AAEL027637", "target": "AAEL027637", "value": 12}, {"source": "AAEL027637", "target": "AAEL027637", "value": 12}, {"source": "AAEL027637", "target": "AAEL027637", "value": 13}, {"source": "AAEL027637", "target": "AAEL027637", "value": 14}, {"source": "AAEL027637", "target": "AAEL027637", "value": 15}, {"source": "AAEL027637", "target": "AAEL027637", "value": 15}, {"source": "AAEL027637", "target": "AAEL027637", "value": 15}, {"source": "AAEL027637", "target": "AAEL027637", "value": 12}, {"source": "AAEL027637", "target": "AAEL027637", "value": 12}, {"source": "AAEL027637", "target": "AAEL027637", "value": 12}, {"source": "AAEL027637", "target": "AAEL027637", "value": 12}, {"source": "AAEL027637", "target": "AAEL027637", "value": 13}, {"source": "AAEL027637", "target": "AAEL027637", "value": 14}, {"source": "AAEL027637", "target": "AAEL027637", "value": 11}, {"source": "AAEL027637", "target": "AAEL027637", "value": 12}, {"source": "AAEL027637", "target": "AAEL027637", "value": 13}, {"source": "AAEL027637", "target": "AAEL027637", "value": 14}, {"source": "AAEL027637", "target": "AAEL027637", "value": 13}, {"source": "AAEL027637", "target": "AAEL027637", "value": 14}, {"source": "AAEL027637", "target": "AAEL027637", "value": 15}, {"source": "AAEL027637", "target": "AAEL027637", "value": 16}, {"source": "AAEL027637", "target": "AAEL027637", "value": 16}, {"source": "AAEL027637", "target": "AAEL027637", "value": 16}, {"source": "AAEL027637", "target": "AAEL027637", "value": 14}, {"source": "AAEL027637", "target": "AAEL027637", "value": 14}, {"source": "AAEL027637", "target": "AAEL027637", "value": 14}, {"source": "AAEL027637", "target": "AAEL027637", "value": 14}, {"source": "AAEL027637", "target": "AAEL027637", "value": 14}, {"source": "AAEL027637", "target": "AAEL027637", "value": 14}, {"source": "AAEL027637", "target": "AAEL027637", "value": 14}, {"source": "AAEL027637", "target": "AAEL027637", "value": 14}, {"source": "AAEL027637", "target": "AAEL027637", "value": 14}, {"source": "AAEL027637", "target": "AAEL027637", "value": 14}, {"source": "AAEL027637", "target": "AAEL027637", "value": 15}, {"source": "AAEL027637", "target": "AAEL027637", "value": 14}, {"source": "AAEL027637", "target": "AAEL027637", "value": 15}, {"source": "AAEL027637", "target": "AAEL027637", "value": 13}, {"source": "AAEL027637", "target": "AAEL027637", "value": 14}, {"source": "AAEL027637", "target": "AAEL027637", "value": 15}, {"source": "AAEL027637", "target": "AAEL027637", "value": 14}, {"source": "AAEL027637", "target": "AAEL027637", "value": 15}, {"source": "AAEL027637", "target": "AAEL027637", "value": 16}, {"source": "AAEL027637", "target": "AAEL027637", "value": 17}, {"source": "AAEL027637", "target": "AAEL027637", "value": 17}, {"source": "AAEL027637", "target": "AAEL027637", "value": 17}, {"source": "AAEL027637", "target": "AAEL027637", "value": 15}, {"source": "AAEL027637", "target": "AAEL027637", "value": 16}, {"source": "AAEL027637", "target": "AAEL027637", "value": 15}, {"source": "AAEL027637", "target": "AAEL027637", "value": 16}, {"source": "AAEL027637", "target": "AAEL027637", "value": 14}, {"source": "AAEL027637", "target": "AAEL027637", "value": 15}, {"source": "AAEL027637", "target": "AAEL027637", "value": 16}, {"source": "AAEL027637", "target": "AAEL027637", "value": 15}, {"source": "AAEL027637", "target": "AAEL027637", "value": 16}, {"source": "AAEL027637", "target": "AAEL027637", "value": 17}, {"source": "AAEL027637", "target": "AAEL027637", "value": 18}, {"source": "AAEL027637", "target": "AAEL027637", "value": 18}, {"source": "AAEL027637", "target": "AAEL027637", "value": 18}, {"source": "AAEL027637", "target": "AAEL027637", "value": 15}, {"source": "AAEL027637", "target": "AAEL027637", "value": 16}, {"source": "AAEL027637", "target": "AAEL027637", "value": 17}, {"source": "AAEL027637", "target": "AAEL027637", "value": 18}, {"source": "AAEL027637", "target": "AAEL027637", "value": 18}, {"source": "AAEL027637", "target": "AAEL027637", "value": 18}, {"source": "AAEL027637", "target": "AAEL027637", "value": 15}, {"source": "AAEL027637", "target": "AAEL027637", "value": 16}, {"source": "AAEL027637", "target": "AAEL027637", "value": 17}, {"source": "AAEL027637", "target": "AAEL027637", "value": 18}, {"source": "AAEL027637", "target": "AAEL027637", "value": 18}, {"source": "AAEL027637", "target": "AAEL027637", "value": 18}, {"source": "AAEL027637", "target": "AAEL027637", "value": 18}, {"source": "AAEL027637", "target": "AAEL027637", "value": 20}, {"source": "AAEL027637", "target": "AAEL027637", "value": 20}, {"source": "AAEL027637", "target": "AAEL027637", "value": 20}, {"source": "AAEL027637", "target": "AAEL027637", "value": 20}, {"source": "AAEL027637", "target": "AAEL003318", "value": 14}, {"source": "AAEL027637", "target": "AAEL003318", "value": 14}, {"source": "AAEL027637", "target": "AAEL011756", "value": 7}, {"source": "AAEL027637", "target": "AAEL026602", "value": 7}, {"source": "AAEL027637", "target": "AAEL011756", "value": 8}, {"source": "AAEL027637", "target": "AAEL026602", "value": 8}, {"source": "AAEL027637", "target": "AAEL011756", "value": 9}, {"source": "AAEL027637", "target": "AAEL026602", "value": 9}, {"source": "AAEL027637", "target": "AAEL011756", "value": 10}, {"source": "AAEL027637", "target": "AAEL026602", "value": 10}, {"source": "AAEL027637", "target": "AAEL011756", "value": 10}, {"source": "AAEL027637", "target": "AAEL026602", "value": 10}, {"source": "AAEL027637", "target": "AAEL011756", "value": 10}, {"source": "AAEL027637", "target": "AAEL026602", "value": 10}, {"source": "AAEL027637", "target": "AAEL011756", "value": 12}, {"source": "AAEL027637", "target": "AAEL026602", "value": 12}, {"source": "AAEL027637", "target": "AAEL011756", "value": 12}, {"source": "AAEL027637", "target": "AAEL026602", "value": 12}, {"source": "AAEL011756", "target": "AAEL027637", "value": 5}, {"source": "AAEL026602", "target": "AAEL027637", "value": 5}, {"source": "AAEL011756", "target": "AAEL027637", "value": 7}, {"source": "AAEL026602", "target": "AAEL027637", "value": 7}, {"source": "AAEL011756", "target": "AAEL006381", "value": 6}, {"source": "AAEL026602", "target": "AAEL006381", "value": 6}, {"source": "AAEL011756", "target": "AAEL006381", "value": 8}, {"source": "AAEL026602", "target": "AAEL006381", "value": 8}, {"source": "AAEL011756", "target": "AAEL003318", "value": 3}, {"source": "AAEL026602", "target": "AAEL003318", "value": 3}, {"source": "AAEL011756", "target": "AAEL026602", "value": 8}, {"source": "AAEL026602", "target": "AAEL026602", "value": 8}, {"source": "AAEL011756", "target": "AAEL027637", "value": 10}, {"source": "AAEL026602", "target": "AAEL027637", "value": 10}, {"source": "AAEL011756", "target": "AAEL011756", "value": 2}, {"source": "AAEL011756", "target": "AAEL026602", "value": 2}, {"source": "AAEL026602", "target": "AAEL011756", "value": 2}, {"source": "AAEL026602", "target": "AAEL026602", "value": 2}, {"source": "AAEL011756", "target": "AAEL011756", "value": 4}, {"source": "AAEL011756", "target": "AAEL026602", "value": 4}, {"source": "AAEL026602", "target": "AAEL011756", "value": 4}, {"source": "AAEL026602", "target": "AAEL026602", "value": 4}, {"source": "AAEL011756", "target": "AAEL011756", "value": 4}, {"source": "AAEL026602", "target": "AAEL011756", "value": 4}, {"source": "AAEL011756", "target": "AAEL011756", "value": 6}, {"source": "AAEL026602", "target": "AAEL011756", "value": 6}, {"source": "AAEL011756", "target": "AAEL006381", "value": 2}, {"source": "AAEL026602", "target": "AAEL006381", "value": 2}, {"source": "AAEL011756", "target": "AAEL006381", "value": 4}, {"source": "AAEL026602", "target": "AAEL006381", "value": 4}, {"source": "AAEL011756", "target": "AAEL006381", "value": 3}, {"source": "AAEL026602", "target": "AAEL006381", "value": 3}, {"source": "AAEL011756", "target": "AAEL006381", "value": 5}, {"source": "AAEL026602", "target": "AAEL006381", "value": 5}, {"source": "AAEL011756", "target": "AAEL003318", "value": 4}, {"source": "AAEL026602", "target": "AAEL003318", "value": 4}, {"source": "AAEL011756", "target": "AAEL006381", "value": 6}, {"source": "AAEL026602", "target": "AAEL006381", "value": 6}, {"source": "AAEL011756", "target": "AAEL027637", "value": 7}, {"source": "AAEL011756", "target": "AAEL027637", "value": 9}, {"source": "AAEL011756", "target": "AAEL006381", "value": 8}, {"source": "AAEL011756", "target": "AAEL006381", "value": 10}, {"source": "AAEL011756", "target": "AAEL003318", "value": 5}, {"source": "AAEL011756", "target": "AAEL026602", "value": 10}, {"source": "AAEL011756", "target": "AAEL027637", "value": 12}, {"source": "AAEL011756", "target": "AAEL011756", "value": 4}, {"source": "AAEL011756", "target": "AAEL026602", "value": 4}, {"source": "AAEL011756", "target": "AAEL011756", "value": 6}, {"source": "AAEL011756", "target": "AAEL026602", "value": 6}, {"source": "AAEL011756", "target": "AAEL011756", "value": 2}, {"source": "AAEL011756", "target": "AAEL011756", "value": 4}, {"source": "AAEL011756", "target": "AAEL011756", "value": 6}, {"source": "AAEL011756", "target": "AAEL011756", "value": 8}, {"source": "AAEL011756", "target": "AAEL006381", "value": 4}, {"source": "AAEL011756", "target": "AAEL006381", "value": 6}, {"source": "AAEL011756", "target": "AAEL006381", "value": 5}, {"source": "AAEL011756", "target": "AAEL006381", "value": 7}, {"source": "AAEL011756", "target": "AAEL003318", "value": 6}, {"source": "AAEL011756", "target": "AAEL006381", "value": 8}, {"source": "AAEL006381", "target": "AAEL027637", "value": 5}, {"source": "AAEL006381", "target": "AAEL027637", "value": 7}, {"source": "AAEL006381", "target": "AAEL006381", "value": 6}, {"source": "AAEL006381", "target": "AAEL006381", "value": 8}, {"source": "AAEL006381", "target": "AAEL003318", "value": 3}, {"source": "AAEL006381", "target": "AAEL026602", "value": 8}, {"source": "AAEL006381", "target": "AAEL027637", "value": 10}, {"source": "AAEL006381", "target": "AAEL011756", "value": 2}, {"source": "AAEL006381", "target": "AAEL026602", "value": 2}, {"source": "AAEL006381", "target": "AAEL011756", "value": 4}, {"source": "AAEL006381", "target": "AAEL026602", "value": 4}, {"source": "AAEL006381", "target": "AAEL011756", "value": 4}, {"source": "AAEL006381", "target": "AAEL011756", "value": 6}, {"source": "AAEL006381", "target": "AAEL006381", "value": 2}, {"source": "AAEL006381", "target": "AAEL006381", "value": 4}, {"source": "AAEL006381", "target": "AAEL006381", "value": 3}, {"source": "AAEL006381", "target": "AAEL006381", "value": 5}, {"source": "AAEL006381", "target": "AAEL003318", "value": 4}, {"source": "AAEL006381", "target": "AAEL006381", "value": 6}, {"source": "AAEL006381", "target": "AAEL027637", "value": 6}, {"source": "AAEL006381", "target": "AAEL027637", "value": 8}, {"source": "AAEL006381", "target": "AAEL006381", "value": 5}, {"source": "AAEL006381", "target": "AAEL006381", "value": 7}, {"source": "AAEL006381", "target": "AAEL006381", "value": 9}, {"source": "AAEL006381", "target": "AAEL003318", "value": 4}, {"source": "AAEL006381", "target": "AAEL026602", "value": 9}, {"source": "AAEL006381", "target": "AAEL027637", "value": 11}, {"source": "AAEL006381", "target": "AAEL011756", "value": 3}, {"source": "AAEL006381", "target": "AAEL026602", "value": 3}, {"source": "AAEL006381", "target": "AAEL011756", "value": 5}, {"source": "AAEL006381", "target": "AAEL026602", "value": 5}, {"source": "AAEL006381", "target": "AAEL011756", "value": 5}, {"source": "AAEL006381", "target": "AAEL011756", "value": 7}, {"source": "AAEL006381", "target": "AAEL006381", "value": 3}, {"source": "AAEL006381", "target": "AAEL006381", "value": 5}, {"source": "AAEL006381", "target": "AAEL006381", "value": 2}, {"source": "AAEL006381", "target": "AAEL006381", "value": 4}, {"source": "AAEL006381", "target": "AAEL006381", "value": 6}, {"source": "AAEL006381", "target": "AAEL003318", "value": 5}, {"source": "AAEL006381", "target": "AAEL006381", "value": 7}, {"source": "AAEL003318", "target": "AAEL027637", "value": 7}, {"source": "AAEL003318", "target": "AAEL006381", "value": 8}, {"source": "AAEL003318", "target": "AAEL003318", "value": 3}, {"source": "AAEL003318", "target": "AAEL026602", "value": 8}, {"source": "AAEL003318", "target": "AAEL027637", "value": 10}, {"source": "AAEL003318", "target": "AAEL011756", "value": 4}, {"source": "AAEL003318", "target": "AAEL026602", "value": 4}, {"source": "AAEL003318", "target": "AAEL011756", "value": 6}, {"source": "AAEL003318", "target": "AAEL006381", "value": 4}, {"source": "AAEL003318", "target": "AAEL006381", "value": 5}, {"source": "AAEL003318", "target": "AAEL003318", "value": 2}, {"source": "AAEL003318", "target": "AAEL003318", "value": 4}, {"source": "AAEL003318", "target": "AAEL006381", "value": 6}, {"source": "AAEL006381", "target": "AAEL027637", "value": 9}, {"source": "AAEL006381", "target": "AAEL006381", "value": 10}, {"source": "AAEL006381", "target": "AAEL003318", "value": 5}, {"source": "AAEL006381", "target": "AAEL026602", "value": 4}, {"source": "AAEL006381", "target": "AAEL026602", "value": 6}, {"source": "AAEL006381", "target": "AAEL026602", "value": 8}, {"source": "AAEL006381", "target": "AAEL026602", "value": 10}, {"source": "AAEL006381", "target": "AAEL027637", "value": 5}, {"source": "AAEL006381", "target": "AAEL027637", "value": 5}, {"source": "AAEL006381", "target": "AAEL027637", "value": 7}, {"source": "AAEL006381", "target": "AAEL027637", "value": 8}, {"source": "AAEL006381", "target": "AAEL027637", "value": 9}, {"source": "AAEL006381", "target": "AAEL027637", "value": 10}, {"source": "AAEL006381", "target": "AAEL027637", "value": 10}, {"source": "AAEL006381", "target": "AAEL027637", "value": 12}, {"source": "AAEL006381", "target": "AAEL011756", "value": 6}, {"source": "AAEL006381", "target": "AAEL026602", "value": 6}, {"source": "AAEL006381", "target": "AAEL011756", "value": 8}, {"source": "AAEL006381", "target": "AAEL006381", "value": 6}, {"source": "AAEL006381", "target": "AAEL006381", "value": 7}, {"source": "AAEL006381", "target": "AAEL003318", "value": 6}, {"source": "AAEL006381", "target": "AAEL006381", "value": 2}, {"source": "AAEL006381", "target": "AAEL006381", "value": 4}, {"source": "AAEL006381", "target": "AAEL006381", "value": 6}, {"source": "AAEL006381", "target": "AAEL006381", "value": 8}, {"source": "AAEL003318", "target": "AAEL006381", "value": 11}, {"source": "AAEL003318", "target": "AAEL006381", "value": 12}, {"source": "AAEL003318", "target": "AAEL003318", "value": 4}, {"source": "AAEL003318", "target": "AAEL003318", "value": 5}, {"source": "AAEL003318", "target": "AAEL003318", "value": 7}, {"source": "AAEL003318", "target": "AAEL003318", "value": 9}, {"source": "AAEL003318", "target": "AAEL003318", "value": 11}, {"source": "AAEL003318", "target": "AAEL027637", "value": 14}, {"source": "AAEL003318", "target": "AAEL027637", "value": 14}, {"source": "AAEL003318", "target": "AAEL003318", "value": 2}, {"source": "AAEL003318", "target": "AAEL003318", "value": 4}, {"source": "AAEL003318", "target": "AAEL003318", "value": 6}, {"source": "AAEL003318", "target": "AAEL003318", "value": 8}, {"source": "AAEL003318", "target": "AAEL011756", "value": 6}, {"source": "AAEL003318", "target": "AAEL026602", "value": 6}, {"source": "AAEL011756", "target": "AAEL006381", "value": 6}, {"source": "AAEL026602", "target": "AAEL006381", "value": 6}, {"source": "AAEL011756", "target": "AAEL006381", "value": 7}, {"source": "AAEL026602", "target": "AAEL006381", "value": 7}, {"source": "AAEL011756", "target": "AAEL006381", "value": 8}, {"source": "AAEL026602", "target": "AAEL006381", "value": 8}, {"source": "AAEL011756", "target": "AAEL006381", "value": 8}, {"source": "AAEL026602", "target": "AAEL006381", "value": 8}, {"source": "AAEL011756", "target": "AAEL006381", "value": 8}, {"source": "AAEL026602", "target": "AAEL006381", "value": 8}, {"source": "AAEL011756", "target": "AAEL006381", "value": 9}, {"source": "AAEL026602", "target": "AAEL006381", "value": 9}, {"source": "AAEL011756", "target": "AAEL006381", "value": 10}, {"source": "AAEL026602", "target": "AAEL006381", "value": 10}, {"source": "AAEL011756", "target": "AAEL003318", "value": 9}, {"source": "AAEL026602", "target": "AAEL003318", "value": 9}, {"source": "AAEL011756", "target": "AAEL027637", "value": 7}, {"source": "AAEL026602", "target": "AAEL027637", "value": 7}, {"source": "AAEL011756", "target": "AAEL027637", "value": 8}, {"source": "AAEL026602", "target": "AAEL027637", "value": 8}, {"source": "AAEL011756", "target": "AAEL027637", "value": 9}, {"source": "AAEL026602", "target": "AAEL027637", "value": 9}, {"source": "AAEL011756", "target": "AAEL027637", "value": 10}, {"source": "AAEL026602", "target": "AAEL027637", "value": 10}, {"source": "AAEL011756", "target": "AAEL027637", "value": 10}, {"source": "AAEL026602", "target": "AAEL027637", "value": 10}, {"source": "AAEL011756", "target": "AAEL027637", "value": 10}, {"source": "AAEL026602", "target": "AAEL027637", "value": 10}, {"source": "AAEL011756", "target": "AAEL027637", "value": 12}, {"source": "AAEL026602", "target": "AAEL027637", "value": 12}, {"source": "AAEL011756", "target": "AAEL027637", "value": 12}, {"source": "AAEL026602", "target": "AAEL027637", "value": 12}, {"source": "AAEL011756", "target": "AAEL003318", "value": 6}, {"source": "AAEL026602", "target": "AAEL003318", "value": 6}, {"source": "AAEL011756", "target": "AAEL011756", "value": 2}, {"source": "AAEL011756", "target": "AAEL026602", "value": 2}, {"source": "AAEL026602", "target": "AAEL011756", "value": 2}, {"source": "AAEL026602", "target": "AAEL026602", "value": 2}, {"source": "AAEL011756", "target": "AAEL011756", "value": 4}, {"source": "AAEL011756", "target": "AAEL026602", "value": 4}, {"source": "AAEL026602", "target": "AAEL011756", "value": 4}, {"source": "AAEL026602", "target": "AAEL026602", "value": 4}]